{"0": {"NR": "0", "SYSCALL NAME": "restart_syscall", "references": "man/ cs/", "r7": "0", "ARG0 (r0)": "-", "ARG1 (r1)": "-", "ARG2 (r2)": "-", "ARG3 (r3)": "-", "ARG4 (r4)": "-", "ARG5 (r5)": "-"}, "1": {"NR": "1", "SYSCALL NAME": "exit", "references": "man/ cs/", "r7": "1", "ARG0 (r0)": "int error_code", "ARG1 (r1)": "-", "ARG2 (r2)": "-", "ARG3 (r3)": "-", "ARG4 (r4)": "-", "ARG5 (r5)": "-"}, "2": {"NR": "2", "SYSCALL NAME": "fork", "references": "man/ cs/", "r7": "2", "ARG0 (r0)": "-", "ARG1 (r1)": "-", "ARG2 (r2)": "-", "ARG3 (r3)": "-", "ARG4 (r4)": "-", "ARG5 (r5)": "-"}, "3": {"NR": "3", "SYSCALL NAME": "read", "references": "man/ cs/", "r7": "3", "ARG0 (r0)": "unsigned int fd", "ARG1 (r1)": "char *buf", "ARG2 (r2)": "size_t count", "ARG3 (r3)": "-", "ARG4 (r4)": "-", "ARG5 (r5)": "-"}, "4": {"NR": "4", "SYSCALL NAME": "write", "references": "man/ cs/", "r7": "4", "ARG0 (r0)": "unsigned int fd", "ARG1 (r1)": "const char *buf", "ARG2 (r2)": "size_t count", "ARG3 (r3)": "-", "ARG4 (r4)": "-", "ARG5 (r5)": "-"}, "5": {"NR": "5", "SYSCALL NAME": "open", "references": "man/ cs/", "r7": "5", "ARG0 (r0)": "const char *filename", "ARG1 (r1)": "int flags", "ARG2 (r2)": "umode_t mode", "ARG3 (r3)": "-", "ARG4 (r4)": "-", "ARG5 (r5)": "-"}, "6": {"NR": "6", "SYSCALL NAME": "close", "references": "man/ cs/", "r7": "6", "ARG0 (r0)": "unsigned int fd", "ARG1 (r1)": "-", "ARG2 (r2)": "-", "ARG3 (r3)": "-", "ARG4 (r4)": "-", "ARG5 (r5)": "-"}, "7": {"NR": "7", "SYSCALL NAME": "not implemented", "references": "", "r7": "7", "ARG0 (r0)": "", "ARG1 (r1)": "", "ARG2 (r2)": "", "ARG3 (r3)": "", "ARG4 (r4)": "", "ARG5 (r5)": ""}, "8": {"NR": "8", "SYSCALL NAME": "creat", "references": "man/ cs/", "r7": "8", "ARG0 (r0)": "const char *pathname", "ARG1 (r1)": "umode_t mode", "ARG2 (r2)": "-", "ARG3 (r3)": "-", "ARG4 (r4)": "-", "ARG5 (r5)": "-"}, "9": {"NR": "9", "SYSCALL NAME": "link", "references": "man/ cs/", "r7": "9", "ARG0 (r0)": "const char *oldname", "ARG1 (r1)": "const char *newname", "ARG2 (r2)": "-", "ARG3 (r3)": "-", "ARG4 (r4)": "-", "ARG5 (r5)": "-"}, "10": {"NR": "10", "SYSCALL NAME": "unlink", "references": "man/ cs/", "r7": "A", "ARG0 (r0)": "const char *pathname", "ARG1 (r1)": "-", "ARG2 (r2)": "-", "ARG3 (r3)": "-", "ARG4 (r4)": "-", "ARG5 (r5)": "-"}, "11": {"NR": "11", "SYSCALL NAME": "execve", "references": "man/ cs/", "r7": "B", "ARG0 (r0)": "const char *filename", "ARG1 (r1)": "const char *const *argv", "ARG2 (r2)": "const char *const *envp", "ARG3 (r3)": "-", "ARG4 (r4)": "-", "ARG5 (r5)": "-"}, "12": {"NR": "12", "SYSCALL NAME": "chdir", "references": "man/ cs/", "r7": "C", "ARG0 (r0)": "const char *filename", "ARG1 (r1)": "-", "ARG2 (r2)": "-", "ARG3 (r3)": "-", "ARG4 (r4)": "-", "ARG5 (r5)": "-"}, "13": {"NR": "13", "SYSCALL NAME": "not implemented", "references": "", "r7": "D", "ARG0 (r0)": "", "ARG1 (r1)": "", "ARG2 (r2)": "", "ARG3 (r3)": "", "ARG4 (r4)": "", "ARG5 (r5)": ""}, "14": {"NR": "14", "SYSCALL NAME": "mknod", "references": "man/ cs/", "r7": "E", "ARG0 (r0)": "const char *filename", "ARG1 (r1)": "umode_t mode", "ARG2 (r2)": "unsigned dev", "ARG3 (r3)": "-", "ARG4 (r4)": "-", "ARG5 (r5)": "-"}, "15": {"NR": "15", "SYSCALL NAME": "chmod", "references": "man/ cs/", "r7": "F", "ARG0 (r0)": "const char *filename", "ARG1 (r1)": "umode_t mode", "ARG2 (r2)": "-", "ARG3 (r3)": "-", "ARG4 (r4)": "-", "ARG5 (r5)": "-"}, "16": {"NR": "16", "SYSCALL NAME": "lchown", "references": "man/ cs/", "r7": "10", "ARG0 (r0)": "const char *filename", "ARG1 (r1)": "uid_t user", "ARG2 (r2)": "gid_t group", "ARG3 (r3)": "-", "ARG4 (r4)": "-", "ARG5 (r5)": "-"}, "17": {"NR": "17", "SYSCALL NAME": "not implemented", "references": "", "r7": "11", "ARG0 (r0)": "", "ARG1 (r1)": "", "ARG2 (r2)": "", "ARG3 (r3)": "", "ARG4 (r4)": "", "ARG5 (r5)": ""}, "18": {"NR": "18", "SYSCALL NAME": "not implemented", "references": "", "r7": "12", "ARG0 (r0)": "", "ARG1 (r1)": "", "ARG2 (r2)": "", "ARG3 (r3)": "", "ARG4 (r4)": "", "ARG5 (r5)": ""}, "19": {"NR": "19", "SYSCALL NAME": "lseek", "references": "man/ cs/", "r7": "13", "ARG0 (r0)": "unsigned int fd", "ARG1 (r1)": "off_t offset", "ARG2 (r2)": "unsigned int whence", "ARG3 (r3)": "-", "ARG4 (r4)": "-", "ARG5 (r5)": "-"}, "20": {"NR": "20", "SYSCALL NAME": "getpid", "references": "man/ cs/", "r7": "14", "ARG0 (r0)": "-", "ARG1 (r1)": "-", "ARG2 (r2)": "-", "ARG3 (r3)": "-", "ARG4 (r4)": "-", "ARG5 (r5)": "-"}, "21": {"NR": "21", "SYSCALL NAME": "mount", "references": "man/ cs/", "r7": "15", "ARG0 (r0)": "char *dev_name", "ARG1 (r1)": "char *dir_name", "ARG2 (r2)": "char *type", "ARG3 (r3)": "unsigned long flags", "ARG4 (r4)": "void *data", "ARG5 (r5)": "-"}, "22": {"NR": "22", "SYSCALL NAME": "not implemented", "references": "", "r7": "16", "ARG0 (r0)": "", "ARG1 (r1)": "", "ARG2 (r2)": "", "ARG3 (r3)": "", "ARG4 (r4)": "", "ARG5 (r5)": ""}, "23": {"NR": "23", "SYSCALL NAME": "setuid", "references": "man/ cs/", "r7": "17", "ARG0 (r0)": "uid_t uid", "ARG1 (r1)": "-", "ARG2 (r2)": "-", "ARG3 (r3)": "-", "ARG4 (r4)": "-", "ARG5 (r5)": "-"}, "24": {"NR": "24", "SYSCALL NAME": "getuid", "references": "man/ cs/", "r7": "18", "ARG0 (r0)": "-", "ARG1 (r1)": "-", "ARG2 (r2)": "-", "ARG3 (r3)": "-", "ARG4 (r4)": "-", "ARG5 (r5)": "-"}, "25": {"NR": "25", "SYSCALL NAME": "not implemented", "references": "", "r7": "19", "ARG0 (r0)": "", "ARG1 (r1)": "", "ARG2 (r2)": "", "ARG3 (r3)": "", "ARG4 (r4)": "", "ARG5 (r5)": ""}, "26": {"NR": "26", "SYSCALL NAME": "ptrace", "references": "man/ cs/", "r7": "1A", "ARG0 (r0)": "long request", "ARG1 (r1)": "long pid", "ARG2 (r2)": "unsigned long addr", "ARG3 (r3)": "unsigned long data", "ARG4 (r4)": "-", "ARG5 (r5)": "-"}, "27": {"NR": "27", "SYSCALL NAME": "not implemented", "references": "", "r7": "1B", "ARG0 (r0)": "", "ARG1 (r1)": "", "ARG2 (r2)": "", "ARG3 (r3)": "", "ARG4 (r4)": "", "ARG5 (r5)": ""}, "28": {"NR": "28", "SYSCALL NAME": "not implemented", "references": "", "r7": "1C", "ARG0 (r0)": "", "ARG1 (r1)": "", "ARG2 (r2)": "", "ARG3 (r3)": "", "ARG4 (r4)": "", "ARG5 (r5)": ""}, "29": {"NR": "29", "SYSCALL NAME": "pause", "references": "man/ cs/", "r7": "1D", "ARG0 (r0)": "-", "ARG1 (r1)": "-", "ARG2 (r2)": "-", "ARG3 (r3)": "-", "ARG4 (r4)": "-", "ARG5 (r5)": "-"}, "30": {"NR": "30", "SYSCALL NAME": "not implemented", "references": "", "r7": "1E", "ARG0 (r0)": "", "ARG1 (r1)": "", "ARG2 (r2)": "", "ARG3 (r3)": "", "ARG4 (r4)": "", "ARG5 (r5)": ""}, "31": {"NR": "31", "SYSCALL NAME": "not implemented", "references": "", "r7": "1F", "ARG0 (r0)": "", "ARG1 (r1)": "", "ARG2 (r2)": "", "ARG3 (r3)": "", "ARG4 (r4)": "", "ARG5 (r5)": ""}, "32": {"NR": "32", "SYSCALL NAME": "not implemented", "references": "", "r7": "20", "ARG0 (r0)": "", "ARG1 (r1)": "", "ARG2 (r2)": "", "ARG3 (r3)": "", "ARG4 (r4)": "", "ARG5 (r5)": ""}, "33": {"NR": "33", "SYSCALL NAME": "access", "references": "man/ cs/", "r7": "21", "ARG0 (r0)": "const char *filename", "ARG1 (r1)": "int mode", "ARG2 (r2)": "-", "ARG3 (r3)": "-", "ARG4 (r4)": "-", "ARG5 (r5)": "-"}, "34": {"NR": "34", "SYSCALL NAME": "nice", "references": "man/ cs/", "r7": "22", "ARG0 (r0)": "int increment", "ARG1 (r1)": "-", "ARG2 (r2)": "-", "ARG3 (r3)": "-", "ARG4 (r4)": "-", "ARG5 (r5)": "-"}, "35": {"NR": "35", "SYSCALL NAME": "not implemented", "references": "", "r7": "23", "ARG0 (r0)": "", "ARG1 (r1)": "", "ARG2 (r2)": "", "ARG3 (r3)": "", "ARG4 (r4)": "", "ARG5 (r5)": ""}, "36": {"NR": "36", "SYSCALL NAME": "sync", "references": "man/ cs/", "r7": "24", "ARG0 (r0)": "-", "ARG1 (r1)": "-", "ARG2 (r2)": "-", "ARG3 (r3)": "-", "ARG4 (r4)": "-", "ARG5 (r5)": "-"}, "37": {"NR": "37", "SYSCALL NAME": "kill", "references": "man/ cs/", "r7": "25", "ARG0 (r0)": "pid_t pid", "ARG1 (r1)": "int sig", "ARG2 (r2)": "-", "ARG3 (r3)": "-", "ARG4 (r4)": "-", "ARG5 (r5)": "-"}, "38": {"NR": "38", "SYSCALL NAME": "rename", "references": "man/ cs/", "r7": "26", "ARG0 (r0)": "const char *oldname", "ARG1 (r1)": "const char *newname", "ARG2 (r2)": "-", "ARG3 (r3)": "-", "ARG4 (r4)": "-", "ARG5 (r5)": "-"}, "39": {"NR": "39", "SYSCALL NAME": "mkdir", "references": "man/ cs/", "r7": "27", "ARG0 (r0)": "const char *pathname", "ARG1 (r1)": "umode_t mode", "ARG2 (r2)": "-", "ARG3 (r3)": "-", "ARG4 (r4)": "-", "ARG5 (r5)": "-"}, "40": {"NR": "40", "SYSCALL NAME": "rmdir", "references": "man/ cs/", "r7": "28", "ARG0 (r0)": "const char *pathname", "ARG1 (r1)": "-", "ARG2 (r2)": "-", "ARG3 (r3)": "-", "ARG4 (r4)": "-", "ARG5 (r5)": "-"}, "41": {"NR": "41", "SYSCALL NAME": "dup", "references": "man/ cs/", "r7": "29", "ARG0 (r0)": "unsigned int fildes", "ARG1 (r1)": "-", "ARG2 (r2)": "-", "ARG3 (r3)": "-", "ARG4 (r4)": "-", "ARG5 (r5)": "-"}, "42": {"NR": "42", "SYSCALL NAME": "pipe", "references": "man/ cs/", "r7": "2A", "ARG0 (r0)": "int *fildes", "ARG1 (r1)": "-", "ARG2 (r2)": "-", "ARG3 (r3)": "-", "ARG4 (r4)": "-", "ARG5 (r5)": "-"}, "43": {"NR": "43", "SYSCALL NAME": "times", "references": "man/ cs/", "r7": "2B", "ARG0 (r0)": "struct tms *tbuf", "ARG1 (r1)": "-", "ARG2 (r2)": "-", "ARG3 (r3)": "-", "ARG4 (r4)": "-", "ARG5 (r5)": "-"}, "44": {"NR": "44", "SYSCALL NAME": "not implemented", "references": "", "r7": "2C", "ARG0 (r0)": "", "ARG1 (r1)": "", "ARG2 (r2)": "", "ARG3 (r3)": "", "ARG4 (r4)": "", "ARG5 (r5)": ""}, "45": {"NR": "45", "SYSCALL NAME": "brk", "references": "man/ cs/", "r7": "2D", "ARG0 (r0)": "unsigned long brk", "ARG1 (r1)": "-", "ARG2 (r2)": "-", "ARG3 (r3)": "-", "ARG4 (r4)": "-", "ARG5 (r5)": "-"}, "46": {"NR": "46", "SYSCALL NAME": "setgid", "references": "man/ cs/", "r7": "2E", "ARG0 (r0)": "gid_t gid", "ARG1 (r1)": "-", "ARG2 (r2)": "-", "ARG3 (r3)": "-", "ARG4 (r4)": "-", "ARG5 (r5)": "-"}, "47": {"NR": "47", "SYSCALL NAME": "getgid", "references": "man/ cs/", "r7": "2F", "ARG0 (r0)": "-", "ARG1 (r1)": "-", "ARG2 (r2)": "-", "ARG3 (r3)": "-", "ARG4 (r4)": "-", "ARG5 (r5)": "-"}, "48": {"NR": "48", "SYSCALL NAME": "not implemented", "references": "", "r7": "30", "ARG0 (r0)": "", "ARG1 (r1)": "", "ARG2 (r2)": "", "ARG3 (r3)": "", "ARG4 (r4)": "", "ARG5 (r5)": ""}, "49": {"NR": "49", "SYSCALL NAME": "geteuid", "references": "man/ cs/", "r7": "31", "ARG0 (r0)": "-", "ARG1 (r1)": "-", "ARG2 (r2)": "-", "ARG3 (r3)": "-", "ARG4 (r4)": "-", "ARG5 (r5)": "-"}, "50": {"NR": "50", "SYSCALL NAME": "getegid", "references": "man/ cs/", "r7": "32", "ARG0 (r0)": "-", "ARG1 (r1)": "-", "ARG2 (r2)": "-", "ARG3 (r3)": "-", "ARG4 (r4)": "-", "ARG5 (r5)": "-"}, "51": {"NR": "51", "SYSCALL NAME": "acct", "references": "man/ cs/", "r7": "33", "ARG0 (r0)": "const char *name", "ARG1 (r1)": "-", "ARG2 (r2)": "-", "ARG3 (r3)": "-", "ARG4 (r4)": "-", "ARG5 (r5)": "-"}, "52": {"NR": "52", "SYSCALL NAME": "umount2", "references": "man/ cs/", "r7": "34", "ARG0 (r0)": "?", "ARG1 (r1)": "?", "ARG2 (r2)": "?", "ARG3 (r3)": "?", "ARG4 (r4)": "?", "ARG5 (r5)": "?"}, "53": {"NR": "53", "SYSCALL NAME": "not implemented", "references": "", "r7": "35", "ARG0 (r0)": "", "ARG1 (r1)": "", "ARG2 (r2)": "", "ARG3 (r3)": "", "ARG4 (r4)": "", "ARG5 (r5)": ""}, "54": {"NR": "54", "SYSCALL NAME": "ioctl", "references": "man/ cs/", "r7": "36", "ARG0 (r0)": "unsigned int fd", "ARG1 (r1)": "unsigned int cmd", "ARG2 (r2)": "unsigned long arg", "ARG3 (r3)": "-", "ARG4 (r4)": "-", "ARG5 (r5)": "-"}, "55": {"NR": "55", "SYSCALL NAME": "fcntl", "references": "man/ cs/", "r7": "37", "ARG0 (r0)": "unsigned int fd", "ARG1 (r1)": "unsigned int cmd", "ARG2 (r2)": "unsigned long arg", "ARG3 (r3)": "-", "ARG4 (r4)": "-", "ARG5 (r5)": "-"}, "56": {"NR": "56", "SYSCALL NAME": "not implemented", "references": "", "r7": "38", "ARG0 (r0)": "", "ARG1 (r1)": "", "ARG2 (r2)": "", "ARG3 (r3)": "", "ARG4 (r4)": "", "ARG5 (r5)": ""}, "57": {"NR": "57", "SYSCALL NAME": "setpgid", "references": "man/ cs/", "r7": "39", "ARG0 (r0)": "pid_t pid", "ARG1 (r1)": "pid_t pgid", "ARG2 (r2)": "-", "ARG3 (r3)": "-", "ARG4 (r4)": "-", "ARG5 (r5)": "-"}, "58": {"NR": "58", "SYSCALL NAME": "not implemented", "references": "", "r7": "3A", "ARG0 (r0)": "", "ARG1 (r1)": "", "ARG2 (r2)": "", "ARG3 (r3)": "", "ARG4 (r4)": "", "ARG5 (r5)": ""}, "59": {"NR": "59", "SYSCALL NAME": "not implemented", "references": "", "r7": "3B", "ARG0 (r0)": "", "ARG1 (r1)": "", "ARG2 (r2)": "", "ARG3 (r3)": "", "ARG4 (r4)": "", "ARG5 (r5)": ""}, "60": {"NR": "60", "SYSCALL NAME": "umask", "references": "man/ cs/", "r7": "3C", "ARG0 (r0)": "int mask", "ARG1 (r1)": "-", "ARG2 (r2)": "-", "ARG3 (r3)": "-", "ARG4 (r4)": "-", "ARG5 (r5)": "-"}, "61": {"NR": "61", "SYSCALL NAME": "chroot", "references": "man/ cs/", "r7": "3D", "ARG0 (r0)": "const char *filename", "ARG1 (r1)": "-", "ARG2 (r2)": "-", "ARG3 (r3)": "-", "ARG4 (r4)": "-", "ARG5 (r5)": "-"}, "62": {"NR": "62", "SYSCALL NAME": "ustat", "references": "man/ cs/", "r7": "3E", "ARG0 (r0)": "unsigned dev", "ARG1 (r1)": "struct ustat *ubuf", "ARG2 (r2)": "-", "ARG3 (r3)": "-", "ARG4 (r4)": "-", "ARG5 (r5)": "-"}, "63": {"NR": "63", "SYSCALL NAME": "dup2", "references": "man/ cs/", "r7": "3F", "ARG0 (r0)": "unsigned int oldfd", "ARG1 (r1)": "unsigned int newfd", "ARG2 (r2)": "-", "ARG3 (r3)": "-", "ARG4 (r4)": "-", "ARG5 (r5)": "-"}, "64": {"NR": "64", "SYSCALL NAME": "getppid", "references": "man/ cs/", "r7": "40", "ARG0 (r0)": "-", "ARG1 (r1)": "-", "ARG2 (r2)": "-", "ARG3 (r3)": "-", "ARG4 (r4)": "-", "ARG5 (r5)": "-"}, "65": {"NR": "65", "SYSCALL NAME": "getpgrp", "references": "man/ cs/", "r7": "41", "ARG0 (r0)": "-", "ARG1 (r1)": "-", "ARG2 (r2)": "-", "ARG3 (r3)": "-", "ARG4 (r4)": "-", "ARG5 (r5)": "-"}, "66": {"NR": "66", "SYSCALL NAME": "setsid", "references": "man/ cs/", "r7": "42", "ARG0 (r0)": "-", "ARG1 (r1)": "-", "ARG2 (r2)": "-", "ARG3 (r3)": "-", "ARG4 (r4)": "-", "ARG5 (r5)": "-"}, "67": {"NR": "67", "SYSCALL NAME": "sigaction", "references": "man/ cs/", "r7": "43", "ARG0 (r0)": "int", "ARG1 (r1)": "const struct old_sigaction *", "ARG2 (r2)": "struct old_sigaction *", "ARG3 (r3)": "-", "ARG4 (r4)": "-", "ARG5 (r5)": "-"}, "68": {"NR": "68", "SYSCALL NAME": "not implemented", "references": "", "r7": "44", "ARG0 (r0)": "", "ARG1 (r1)": "", "ARG2 (r2)": "", "ARG3 (r3)": "", "ARG4 (r4)": "", "ARG5 (r5)": ""}, "69": {"NR": "69", "SYSCALL NAME": "not implemented", "references": "", "r7": "45", "ARG0 (r0)": "", "ARG1 (r1)": "", "ARG2 (r2)": "", "ARG3 (r3)": "", "ARG4 (r4)": "", "ARG5 (r5)": ""}, "70": {"NR": "70", "SYSCALL NAME": "setreuid", "references": "man/ cs/", "r7": "46", "ARG0 (r0)": "uid_t ruid", "ARG1 (r1)": "uid_t euid", "ARG2 (r2)": "-", "ARG3 (r3)": "-", "ARG4 (r4)": "-", "ARG5 (r5)": "-"}, "71": {"NR": "71", "SYSCALL NAME": "setregid", "references": "man/ cs/", "r7": "47", "ARG0 (r0)": "gid_t rgid", "ARG1 (r1)": "gid_t egid", "ARG2 (r2)": "-", "ARG3 (r3)": "-", "ARG4 (r4)": "-", "ARG5 (r5)": "-"}, "72": {"NR": "72", "SYSCALL NAME": "sigsuspend", "references": "man/ cs/", "r7": "48", "ARG0 (r0)": "int unused1", "ARG1 (r1)": "int unused2", "ARG2 (r2)": "old_sigset_t mask", "ARG3 (r3)": "-", "ARG4 (r4)": "-", "ARG5 (r5)": "-"}, "73": {"NR": "73", "SYSCALL NAME": "sigpending", "references": "man/ cs/", "r7": "49", "ARG0 (r0)": "old_sigset_t *uset", "ARG1 (r1)": "-", "ARG2 (r2)": "-", "ARG3 (r3)": "-", "ARG4 (r4)": "-", "ARG5 (r5)": "-"}, "74": {"NR": "74", "SYSCALL NAME": "sethostname", "references": "man/ cs/", "r7": "4A", "ARG0 (r0)": "char *name", "ARG1 (r1)": "int len", "ARG2 (r2)": "-", "ARG3 (r3)": "-", "ARG4 (r4)": "-", "ARG5 (r5)": "-"}, "75": {"NR": "75", "SYSCALL NAME": "setrlimit", "references": "man/ cs/", "r7": "4B", "ARG0 (r0)": "unsigned int resource", "ARG1 (r1)": "struct rlimit *rlim", "ARG2 (r2)": "-", "ARG3 (r3)": "-", "ARG4 (r4)": "-", "ARG5 (r5)": "-"}, "76": {"NR": "76", "SYSCALL NAME": "not implemented", "references": "", "r7": "4C", "ARG0 (r0)": "", "ARG1 (r1)": "", "ARG2 (r2)": "", "ARG3 (r3)": "", "ARG4 (r4)": "", "ARG5 (r5)": ""}, "77": {"NR": "77", "SYSCALL NAME": "getrusage", "references": "man/ cs/", "r7": "4D", "ARG0 (r0)": "int who", "ARG1 (r1)": "struct rusage *ru", "ARG2 (r2)": "-", "ARG3 (r3)": "-", "ARG4 (r4)": "-", "ARG5 (r5)": "-"}, "78": {"NR": "78", "SYSCALL NAME": "gettimeofday", "references": "man/ cs/", "r7": "4E", "ARG0 (r0)": "struct timeval *tv", "ARG1 (r1)": "struct timezone *tz", "ARG2 (r2)": "-", "ARG3 (r3)": "-", "ARG4 (r4)": "-", "ARG5 (r5)": "-"}, "79": {"NR": "79", "SYSCALL NAME": "settimeofday", "references": "man/ cs/", "r7": "4F", "ARG0 (r0)": "struct timeval *tv", "ARG1 (r1)": "struct timezone *tz", "ARG2 (r2)": "-", "ARG3 (r3)": "-", "ARG4 (r4)": "-", "ARG5 (r5)": "-"}, "80": {"NR": "80", "SYSCALL NAME": "getgroups", "references": "man/ cs/", "r7": "50", "ARG0 (r0)": "int gidsetsize", "ARG1 (r1)": "gid_t *grouplist", "ARG2 (r2)": "-", "ARG3 (r3)": "-", "ARG4 (r4)": "-", "ARG5 (r5)": "-"}, "81": {"NR": "81", "SYSCALL NAME": "setgroups", "references": "man/ cs/", "r7": "51", "ARG0 (r0)": "int gidsetsize", "ARG1 (r1)": "gid_t *grouplist", "ARG2 (r2)": "-", "ARG3 (r3)": "-", "ARG4 (r4)": "-", "ARG5 (r5)": "-"}, "82": {"NR": "82", "SYSCALL NAME": "not implemented", "references": "", "r7": "52", "ARG0 (r0)": "", "ARG1 (r1)": "", "ARG2 (r2)": "", "ARG3 (r3)": "", "ARG4 (r4)": "", "ARG5 (r5)": ""}, "83": {"NR": "83", "SYSCALL NAME": "symlink", "references": "man/ cs/", "r7": "53", "ARG0 (r0)": "const char *old", "ARG1 (r1)": "const char *new", "ARG2 (r2)": "-", "ARG3 (r3)": "-", "ARG4 (r4)": "-", "ARG5 (r5)": "-"}, "84": {"NR": "84", "SYSCALL NAME": "not implemented", "references": "", "r7": "54", "ARG0 (r0)": "", "ARG1 (r1)": "", "ARG2 (r2)": "", "ARG3 (r3)": "", "ARG4 (r4)": "", "ARG5 (r5)": ""}, "85": {"NR": "85", "SYSCALL NAME": "readlink", "references": "man/ cs/", "r7": "55", "ARG0 (r0)": "const char *path", "ARG1 (r1)": "char *buf", "ARG2 (r2)": "int bufsiz", "ARG3 (r3)": "-", "ARG4 (r4)": "-", "ARG5 (r5)": "-"}, "86": {"NR": "86", "SYSCALL NAME": "uselib", "references": "man/ cs/", "r7": "56", "ARG0 (r0)": "const char *library", "ARG1 (r1)": "-", "ARG2 (r2)": "-", "ARG3 (r3)": "-", "ARG4 (r4)": "-", "ARG5 (r5)": "-"}, "87": {"NR": "87", "SYSCALL NAME": "swapon", "references": "man/ cs/", "r7": "57", "ARG0 (r0)": "const char *specialfile", "ARG1 (r1)": "int swap_flags", "ARG2 (r2)": "-", "ARG3 (r3)": "-", "ARG4 (r4)": "-", "ARG5 (r5)": "-"}, "88": {"NR": "88", "SYSCALL NAME": "reboot", "references": "man/ cs/", "r7": "58", "ARG0 (r0)": "int magic1", "ARG1 (r1)": "int magic2", "ARG2 (r2)": "unsigned int cmd", "ARG3 (r3)": "void *arg", "ARG4 (r4)": "-", "ARG5 (r5)": "-"}, "89": {"NR": "89", "SYSCALL NAME": "not implemented", "references": "", "r7": "59", "ARG0 (r0)": "", "ARG1 (r1)": "", "ARG2 (r2)": "", "ARG3 (r3)": "", "ARG4 (r4)": "", "ARG5 (r5)": ""}, "90": {"NR": "90", "SYSCALL NAME": "not implemented", "references": "", "r7": "5A", "ARG0 (r0)": "", "ARG1 (r1)": "", "ARG2 (r2)": "", "ARG3 (r3)": "", "ARG4 (r4)": "", "ARG5 (r5)": ""}, "91": {"NR": "91", "SYSCALL NAME": "munmap", "references": "man/ cs/", "r7": "5B", "ARG0 (r0)": "unsigned long addr", "ARG1 (r1)": "size_t len", "ARG2 (r2)": "-", "ARG3 (r3)": "-", "ARG4 (r4)": "-", "ARG5 (r5)": "-"}, "92": {"NR": "92", "SYSCALL NAME": "truncate", "references": "man/ cs/", "r7": "5C", "ARG0 (r0)": "const char *path", "ARG1 (r1)": "long length", "ARG2 (r2)": "-", "ARG3 (r3)": "-", "ARG4 (r4)": "-", "ARG5 (r5)": "-"}, "93": {"NR": "93", "SYSCALL NAME": "ftruncate", "references": "man/ cs/", "r7": "5D", "ARG0 (r0)": "unsigned int fd", "ARG1 (r1)": "unsigned long length", "ARG2 (r2)": "-", "ARG3 (r3)": "-", "ARG4 (r4)": "-", "ARG5 (r5)": "-"}, "94": {"NR": "94", "SYSCALL NAME": "fchmod", "references": "man/ cs/", "r7": "5E", "ARG0 (r0)": "unsigned int fd", "ARG1 (r1)": "umode_t mode", "ARG2 (r2)": "-", "ARG3 (r3)": "-", "ARG4 (r4)": "-", "ARG5 (r5)": "-"}, "95": {"NR": "95", "SYSCALL NAME": "fchown", "references": "man/ cs/", "r7": "5F", "ARG0 (r0)": "unsigned int fd", "ARG1 (r1)": "uid_t user", "ARG2 (r2)": "gid_t group", "ARG3 (r3)": "-", "ARG4 (r4)": "-", "ARG5 (r5)": "-"}, "96": {"NR": "96", "SYSCALL NAME": "getpriority", "references": "man/ cs/", "r7": "60", "ARG0 (r0)": "int which", "ARG1 (r1)": "int who", "ARG2 (r2)": "-", "ARG3 (r3)": "-", "ARG4 (r4)": "-", "ARG5 (r5)": "-"}, "97": {"NR": "97", "SYSCALL NAME": "setpriority", "references": "man/ cs/", "r7": "61", "ARG0 (r0)": "int which", "ARG1 (r1)": "int who", "ARG2 (r2)": "int niceval", "ARG3 (r3)": "-", "ARG4 (r4)": "-", "ARG5 (r5)": "-"}, "98": {"NR": "98", "SYSCALL NAME": "not implemented", "references": "", "r7": "62", "ARG0 (r0)": "", "ARG1 (r1)": "", "ARG2 (r2)": "", "ARG3 (r3)": "", "ARG4 (r4)": "", "ARG5 (r5)": ""}, "99": {"NR": "99", "SYSCALL NAME": "statfs", "references": "man/ cs/", "r7": "63", "ARG0 (r0)": "const char * path", "ARG1 (r1)": "struct statfs *buf", "ARG2 (r2)": "-", "ARG3 (r3)": "-", "ARG4 (r4)": "-", "ARG5 (r5)": "-"}, "100": {"NR": "100", "SYSCALL NAME": "fstatfs", "references": "man/ cs/", "r7": "64", "ARG0 (r0)": "unsigned int fd", "ARG1 (r1)": "struct statfs *buf", "ARG2 (r2)": "-", "ARG3 (r3)": "-", "ARG4 (r4)": "-", "ARG5 (r5)": "-"}, "101": {"NR": "101", "SYSCALL NAME": "not implemented", "references": "", "r7": "65", "ARG0 (r0)": "", "ARG1 (r1)": "", "ARG2 (r2)": "", "ARG3 (r3)": "", "ARG4 (r4)": "", "ARG5 (r5)": ""}, "102": {"NR": "102", "SYSCALL NAME": "not implemented", "references": "", "r7": "66", "ARG0 (r0)": "", "ARG1 (r1)": "", "ARG2 (r2)": "", "ARG3 (r3)": "", "ARG4 (r4)": "", "ARG5 (r5)": ""}, "103": {"NR": "103", "SYSCALL NAME": "syslog", "references": "man/ cs/", "r7": "67", "ARG0 (r0)": "int type", "ARG1 (r1)": "char *buf", "ARG2 (r2)": "int len", "ARG3 (r3)": "-", "ARG4 (r4)": "-", "ARG5 (r5)": "-"}, "104": {"NR": "104", "SYSCALL NAME": "setitimer", "references": "man/ cs/", "r7": "68", "ARG0 (r0)": "int which", "ARG1 (r1)": "struct itimerval *value", "ARG2 (r2)": "struct itimerval *ovalue", "ARG3 (r3)": "-", "ARG4 (r4)": "-", "ARG5 (r5)": "-"}, "105": {"NR": "105", "SYSCALL NAME": "getitimer", "references": "man/ cs/", "r7": "69", "ARG0 (r0)": "int which", "ARG1 (r1)": "struct itimerval *value", "ARG2 (r2)": "-", "ARG3 (r3)": "-", "ARG4 (r4)": "-", "ARG5 (r5)": "-"}, "106": {"NR": "106", "SYSCALL NAME": "stat", "references": "man/ cs/", "r7": "6A", "ARG0 (r0)": "const char *filename", "ARG1 (r1)": "struct __old_kernel_stat *statbuf", "ARG2 (r2)": "-", "ARG3 (r3)": "-", "ARG4 (r4)": "-", "ARG5 (r5)": "-"}, "107": {"NR": "107", "SYSCALL NAME": "lstat", "references": "man/ cs/", "r7": "6B", "ARG0 (r0)": "const char *filename", "ARG1 (r1)": "struct __old_kernel_stat *statbuf", "ARG2 (r2)": "-", "ARG3 (r3)": "-", "ARG4 (r4)": "-", "ARG5 (r5)": "-"}, "108": {"NR": "108", "SYSCALL NAME": "fstat", "references": "man/ cs/", "r7": "6C", "ARG0 (r0)": "unsigned int fd", "ARG1 (r1)": "struct __old_kernel_stat *statbuf", "ARG2 (r2)": "-", "ARG3 (r3)": "-", "ARG4 (r4)": "-", "ARG5 (r5)": "-"}, "109": {"NR": "109", "SYSCALL NAME": "not implemented", "references": "", "r7": "6D", "ARG0 (r0)": "", "ARG1 (r1)": "", "ARG2 (r2)": "", "ARG3 (r3)": "", "ARG4 (r4)": "", "ARG5 (r5)": ""}, "110": {"NR": "110", "SYSCALL NAME": "not implemented", "references": "", "r7": "6E", "ARG0 (r0)": "", "ARG1 (r1)": "", "ARG2 (r2)": "", "ARG3 (r3)": "", "ARG4 (r4)": "", "ARG5 (r5)": ""}, "111": {"NR": "111", "SYSCALL NAME": "vhangup", "references": "man/ cs/", "r7": "6F", "ARG0 (r0)": "-", "ARG1 (r1)": "-", "ARG2 (r2)": "-", "ARG3 (r3)": "-", "ARG4 (r4)": "-", "ARG5 (r5)": "-"}, "112": {"NR": "112", "SYSCALL NAME": "not implemented", "references": "", "r7": "70", "ARG0 (r0)": "", "ARG1 (r1)": "", "ARG2 (r2)": "", "ARG3 (r3)": "", "ARG4 (r4)": "", "ARG5 (r5)": ""}, "113": {"NR": "113", "SYSCALL NAME": "not implemented", "references": "", "r7": "71", "ARG0 (r0)": "", "ARG1 (r1)": "", "ARG2 (r2)": "", "ARG3 (r3)": "", "ARG4 (r4)": "", "ARG5 (r5)": ""}, "114": {"NR": "114", "SYSCALL NAME": "wait4", "references": "man/ cs/", "r7": "72", "ARG0 (r0)": "pid_t pid", "ARG1 (r1)": "int *stat_addr", "ARG2 (r2)": "int options", "ARG3 (r3)": "struct rusage *ru", "ARG4 (r4)": "-", "ARG5 (r5)": "-"}, "115": {"NR": "115", "SYSCALL NAME": "swapoff", "references": "man/ cs/", "r7": "73", "ARG0 (r0)": "const char *specialfile", "ARG1 (r1)": "-", "ARG2 (r2)": "-", "ARG3 (r3)": "-", "ARG4 (r4)": "-", "ARG5 (r5)": "-"}, "116": {"NR": "116", "SYSCALL NAME": "sysinfo", "references": "man/ cs/", "r7": "74", "ARG0 (r0)": "struct sysinfo *info", "ARG1 (r1)": "-", "ARG2 (r2)": "-", "ARG3 (r3)": "-", "ARG4 (r4)": "-", "ARG5 (r5)": "-"}, "117": {"NR": "117", "SYSCALL NAME": "not implemented", "references": "", "r7": "75", "ARG0 (r0)": "", "ARG1 (r1)": "", "ARG2 (r2)": "", "ARG3 (r3)": "", "ARG4 (r4)": "", "ARG5 (r5)": ""}, "118": {"NR": "118", "SYSCALL NAME": "fsync", "references": "man/ cs/", "r7": "76", "ARG0 (r0)": "unsigned int fd", "ARG1 (r1)": "-", "ARG2 (r2)": "-", "ARG3 (r3)": "-", "ARG4 (r4)": "-", "ARG5 (r5)": "-"}, "119": {"NR": "119", "SYSCALL NAME": "sigreturn", "references": "man/ cs/", "r7": "77", "ARG0 (r0)": "?", "ARG1 (r1)": "?", "ARG2 (r2)": "?", "ARG3 (r3)": "?", "ARG4 (r4)": "?", "ARG5 (r5)": "?"}, "120": {"NR": "120", "SYSCALL NAME": "clone", "references": "man/ cs/", "r7": "78", "ARG0 (r0)": "unsigned long", "ARG1 (r1)": "unsigned long", "ARG2 (r2)": "int *", "ARG3 (r3)": "int *", "ARG4 (r4)": "unsigned long", "ARG5 (r5)": "-"}, "121": {"NR": "121", "SYSCALL NAME": "setdomainname", "references": "man/ cs/", "r7": "79", "ARG0 (r0)": "char *name", "ARG1 (r1)": "int len", "ARG2 (r2)": "-", "ARG3 (r3)": "-", "ARG4 (r4)": "-", "ARG5 (r5)": "-"}, "122": {"NR": "122", "SYSCALL NAME": "uname", "references": "man/ cs/", "r7": "7A", "ARG0 (r0)": "struct old_utsname *", "ARG1 (r1)": "-", "ARG2 (r2)": "-", "ARG3 (r3)": "-", "ARG4 (r4)": "-", "ARG5 (r5)": "-"}, "123": {"NR": "123", "SYSCALL NAME": "not implemented", "references": "", "r7": "7B", "ARG0 (r0)": "", "ARG1 (r1)": "", "ARG2 (r2)": "", "ARG3 (r3)": "", "ARG4 (r4)": "", "ARG5 (r5)": ""}, "124": {"NR": "124", "SYSCALL NAME": "adjtimex", "references": "man/ cs/", "r7": "7C", "ARG0 (r0)": "struct __kernel_timex *txc_p", "ARG1 (r1)": "-", "ARG2 (r2)": "-", "ARG3 (r3)": "-", "ARG4 (r4)": "-", "ARG5 (r5)": "-"}, "125": {"NR": "125", "SYSCALL NAME": "mprotect", "references": "man/ cs/", "r7": "7D", "ARG0 (r0)": "unsigned long start", "ARG1 (r1)": "size_t len", "ARG2 (r2)": "unsigned long prot", "ARG3 (r3)": "-", "ARG4 (r4)": "-", "ARG5 (r5)": "-"}, "126": {"NR": "126", "SYSCALL NAME": "sigprocmask", "references": "man/ cs/", "r7": "7E", "ARG0 (r0)": "int how", "ARG1 (r1)": "old_sigset_t *set", "ARG2 (r2)": "old_sigset_t *oset", "ARG3 (r3)": "-", "ARG4 (r4)": "-", "ARG5 (r5)": "-"}, "127": {"NR": "127", "SYSCALL NAME": "not implemented", "references": "", "r7": "7F", "ARG0 (r0)": "", "ARG1 (r1)": "", "ARG2 (r2)": "", "ARG3 (r3)": "", "ARG4 (r4)": "", "ARG5 (r5)": ""}, "128": {"NR": "128", "SYSCALL NAME": "init_module", "references": "man/ cs/", "r7": "80", "ARG0 (r0)": "void *umod", "ARG1 (r1)": "unsigned long len", "ARG2 (r2)": "const char *uargs", "ARG3 (r3)": "-", "ARG4 (r4)": "-", "ARG5 (r5)": "-"}, "129": {"NR": "129", "SYSCALL NAME": "delete_module", "references": "man/ cs/", "r7": "81", "ARG0 (r0)": "const char *name_user", "ARG1 (r1)": "unsigned int flags", "ARG2 (r2)": "-", "ARG3 (r3)": "-", "ARG4 (r4)": "-", "ARG5 (r5)": "-"}, "130": {"NR": "130", "SYSCALL NAME": "not implemented", "references": "", "r7": "82", "ARG0 (r0)": "", "ARG1 (r1)": "", "ARG2 (r2)": "", "ARG3 (r3)": "", "ARG4 (r4)": "", "ARG5 (r5)": ""}, "131": {"NR": "131", "SYSCALL NAME": "quotactl", "references": "man/ cs/", "r7": "83", "ARG0 (r0)": "unsigned int cmd", "ARG1 (r1)": "const char *special", "ARG2 (r2)": "qid_t id", "ARG3 (r3)": "void *addr", "ARG4 (r4)": "-", "ARG5 (r5)": "-"}, "132": {"NR": "132", "SYSCALL NAME": "getpgid", "references": "man/ cs/", "r7": "84", "ARG0 (r0)": "pid_t pid", "ARG1 (r1)": "-", "ARG2 (r2)": "-", "ARG3 (r3)": "-", "ARG4 (r4)": "-", "ARG5 (r5)": "-"}, "133": {"NR": "133", "SYSCALL NAME": "fchdir", "references": "man/ cs/", "r7": "85", "ARG0 (r0)": "unsigned int fd", "ARG1 (r1)": "-", "ARG2 (r2)": "-", "ARG3 (r3)": "-", "ARG4 (r4)": "-", "ARG5 (r5)": "-"}, "134": {"NR": "134", "SYSCALL NAME": "bdflush", "references": "man/ cs/", "r7": "86", "ARG0 (r0)": "int func", "ARG1 (r1)": "long data", "ARG2 (r2)": "-", "ARG3 (r3)": "-", "ARG4 (r4)": "-", "ARG5 (r5)": "-"}, "135": {"NR": "135", "SYSCALL NAME": "sysfs", "references": "man/ cs/", "r7": "87", "ARG0 (r0)": "int option", "ARG1 (r1)": "unsigned long arg1", "ARG2 (r2)": "unsigned long arg2", "ARG3 (r3)": "-", "ARG4 (r4)": "-", "ARG5 (r5)": "-"}, "136": {"NR": "136", "SYSCALL NAME": "personality", "references": "man/ cs/", "r7": "88", "ARG0 (r0)": "unsigned int personality", "ARG1 (r1)": "-", "ARG2 (r2)": "-", "ARG3 (r3)": "-", "ARG4 (r4)": "-", "ARG5 (r5)": "-"}, "137": {"NR": "137", "SYSCALL NAME": "not implemented", "references": "", "r7": "89", "ARG0 (r0)": "", "ARG1 (r1)": "", "ARG2 (r2)": "", "ARG3 (r3)": "", "ARG4 (r4)": "", "ARG5 (r5)": ""}, "138": {"NR": "138", "SYSCALL NAME": "setfsuid", "references": "man/ cs/", "r7": "8A", "ARG0 (r0)": "uid_t uid", "ARG1 (r1)": "-", "ARG2 (r2)": "-", "ARG3 (r3)": "-", "ARG4 (r4)": "-", "ARG5 (r5)": "-"}, "139": {"NR": "139", "SYSCALL NAME": "setfsgid", "references": "man/ cs/", "r7": "8B", "ARG0 (r0)": "gid_t gid", "ARG1 (r1)": "-", "ARG2 (r2)": "-", "ARG3 (r3)": "-", "ARG4 (r4)": "-", "ARG5 (r5)": "-"}, "140": {"NR": "140", "SYSCALL NAME": "_llseek", "references": "man/ cs/", "r7": "8C", "ARG0 (r0)": "?", "ARG1 (r1)": "?", "ARG2 (r2)": "?", "ARG3 (r3)": "?", "ARG4 (r4)": "?", "ARG5 (r5)": "?"}, "141": {"NR": "141", "SYSCALL NAME": "getdents", "references": "man/ cs/", "r7": "8D", "ARG0 (r0)": "unsigned int fd", "ARG1 (r1)": "struct linux_dirent *dirent", "ARG2 (r2)": "unsigned int count", "ARG3 (r3)": "-", "ARG4 (r4)": "-", "ARG5 (r5)": "-"}, "142": {"NR": "142", "SYSCALL NAME": "_newselect", "references": "man/ cs/", "r7": "8E", "ARG0 (r0)": "?", "ARG1 (r1)": "?", "ARG2 (r2)": "?", "ARG3 (r3)": "?", "ARG4 (r4)": "?", "ARG5 (r5)": "?"}, "143": {"NR": "143", "SYSCALL NAME": "flock", "references": "man/ cs/", "r7": "8F", "ARG0 (r0)": "unsigned int fd", "ARG1 (r1)": "unsigned int cmd", "ARG2 (r2)": "-", "ARG3 (r3)": "-", "ARG4 (r4)": "-", "ARG5 (r5)": "-"}, "144": {"NR": "144", "SYSCALL NAME": "msync", "references": "man/ cs/", "r7": "90", "ARG0 (r0)": "unsigned long start", "ARG1 (r1)": "size_t len", "ARG2 (r2)": "int flags", "ARG3 (r3)": "-", "ARG4 (r4)": "-", "ARG5 (r5)": "-"}, "145": {"NR": "145", "SYSCALL NAME": "readv", "references": "man/ cs/", "r7": "91", "ARG0 (r0)": "unsigned long fd", "ARG1 (r1)": "const struct iovec *vec", "ARG2 (r2)": "unsigned long vlen", "ARG3 (r3)": "-", "ARG4 (r4)": "-", "ARG5 (r5)": "-"}, "146": {"NR": "146", "SYSCALL NAME": "writev", "references": "man/ cs/", "r7": "92", "ARG0 (r0)": "unsigned long fd", "ARG1 (r1)": "const struct iovec *vec", "ARG2 (r2)": "unsigned long vlen", "ARG3 (r3)": "-", "ARG4 (r4)": "-", "ARG5 (r5)": "-"}, "147": {"NR": "147", "SYSCALL NAME": "getsid", "references": "man/ cs/", "r7": "93", "ARG0 (r0)": "pid_t pid", "ARG1 (r1)": "-", "ARG2 (r2)": "-", "ARG3 (r3)": "-", "ARG4 (r4)": "-", "ARG5 (r5)": "-"}, "148": {"NR": "148", "SYSCALL NAME": "fdatasync", "references": "man/ cs/", "r7": "94", "ARG0 (r0)": "unsigned int fd", "ARG1 (r1)": "-", "ARG2 (r2)": "-", "ARG3 (r3)": "-", "ARG4 (r4)": "-", "ARG5 (r5)": "-"}, "149": {"NR": "149", "SYSCALL NAME": "_sysctl", "references": "man/ cs/", "r7": "95", "ARG0 (r0)": "?", "ARG1 (r1)": "?", "ARG2 (r2)": "?", "ARG3 (r3)": "?", "ARG4 (r4)": "?", "ARG5 (r5)": "?"}, "150": {"NR": "150", "SYSCALL NAME": "mlock", "references": "man/ cs/", "r7": "96", "ARG0 (r0)": "unsigned long start", "ARG1 (r1)": "size_t len", "ARG2 (r2)": "-", "ARG3 (r3)": "-", "ARG4 (r4)": "-", "ARG5 (r5)": "-"}, "151": {"NR": "151", "SYSCALL NAME": "munlock", "references": "man/ cs/", "r7": "97", "ARG0 (r0)": "unsigned long start", "ARG1 (r1)": "size_t len", "ARG2 (r2)": "-", "ARG3 (r3)": "-", "ARG4 (r4)": "-", "ARG5 (r5)": "-"}, "152": {"NR": "152", "SYSCALL NAME": "mlockall", "references": "man/ cs/", "r7": "98", "ARG0 (r0)": "int flags", "ARG1 (r1)": "-", "ARG2 (r2)": "-", "ARG3 (r3)": "-", "ARG4 (r4)": "-", "ARG5 (r5)": "-"}, "153": {"NR": "153", "SYSCALL NAME": "munlockall", "references": "man/ cs/", "r7": "99", "ARG0 (r0)": "-", "ARG1 (r1)": "-", "ARG2 (r2)": "-", "ARG3 (r3)": "-", "ARG4 (r4)": "-", "ARG5 (r5)": "-"}, "154": {"NR": "154", "SYSCALL NAME": "sched_setparam", "references": "man/ cs/", "r7": "9A", "ARG0 (r0)": "pid_t pid", "ARG1 (r1)": "struct sched_param *param", "ARG2 (r2)": "-", "ARG3 (r3)": "-", "ARG4 (r4)": "-", "ARG5 (r5)": "-"}, "155": {"NR": "155", "SYSCALL NAME": "sched_getparam", "references": "man/ cs/", "r7": "9B", "ARG0 (r0)": "pid_t pid", "ARG1 (r1)": "struct sched_param *param", "ARG2 (r2)": "-", "ARG3 (r3)": "-", "ARG4 (r4)": "-", "ARG5 (r5)": "-"}, "156": {"NR": "156", "SYSCALL NAME": "sched_setscheduler", "references": "man/ cs/", "r7": "9C", "ARG0 (r0)": "pid_t pid", "ARG1 (r1)": "int policy", "ARG2 (r2)": "struct sched_param *param", "ARG3 (r3)": "-", "ARG4 (r4)": "-", "ARG5 (r5)": "-"}, "157": {"NR": "157", "SYSCALL NAME": "sched_getscheduler", "references": "man/ cs/", "r7": "9D", "ARG0 (r0)": "pid_t pid", "ARG1 (r1)": "-", "ARG2 (r2)": "-", "ARG3 (r3)": "-", "ARG4 (r4)": "-", "ARG5 (r5)": "-"}, "158": {"NR": "158", "SYSCALL NAME": "sched_yield", "references": "man/ cs/", "r7": "9E", "ARG0 (r0)": "-", "ARG1 (r1)": "-", "ARG2 (r2)": "-", "ARG3 (r3)": "-", "ARG4 (r4)": "-", "ARG5 (r5)": "-"}, "159": {"NR": "159", "SYSCALL NAME": "sched_get_priority_max", "references": "man/ cs/", "r7": "9F", "ARG0 (r0)": "int policy", "ARG1 (r1)": "-", "ARG2 (r2)": "-", "ARG3 (r3)": "-", "ARG4 (r4)": "-", "ARG5 (r5)": "-"}, "160": {"NR": "160", "SYSCALL NAME": "sched_get_priority_min", "references": "man/ cs/", "r7": "A0", "ARG0 (r0)": "int policy", "ARG1 (r1)": "-", "ARG2 (r2)": "-", "ARG3 (r3)": "-", "ARG4 (r4)": "-", "ARG5 (r5)": "-"}, "161": {"NR": "161", "SYSCALL NAME": "sched_rr_get_interval", "references": "man/ cs/", "r7": "A1", "ARG0 (r0)": "pid_t pid", "ARG1 (r1)": "struct __kernel_timespec *interval", "ARG2 (r2)": "-", "ARG3 (r3)": "-", "ARG4 (r4)": "-", "ARG5 (r5)": "-"}, "162": {"NR": "162", "SYSCALL NAME": "nanosleep", "references": "man/ cs/", "r7": "A2", "ARG0 (r0)": "struct __kernel_timespec *rqtp", "ARG1 (r1)": "struct __kernel_timespec *rmtp", "ARG2 (r2)": "-", "ARG3 (r3)": "-", "ARG4 (r4)": "-", "ARG5 (r5)": "-"}, "163": {"NR": "163", "SYSCALL NAME": "mremap", "references": "man/ cs/", "r7": "A3", "ARG0 (r0)": "unsigned long addr", "ARG1 (r1)": "unsigned long old_len", "ARG2 (r2)": "unsigned long new_len", "ARG3 (r3)": "unsigned long flags", "ARG4 (r4)": "unsigned long new_addr", "ARG5 (r5)": "-"}, "164": {"NR": "164", "SYSCALL NAME": "setresuid", "references": "man/ cs/", "r7": "A4", "ARG0 (r0)": "uid_t ruid", "ARG1 (r1)": "uid_t euid", "ARG2 (r2)": "uid_t suid", "ARG3 (r3)": "-", "ARG4 (r4)": "-", "ARG5 (r5)": "-"}, "165": {"NR": "165", "SYSCALL NAME": "getresuid", "references": "man/ cs/", "r7": "A5", "ARG0 (r0)": "uid_t *ruid", "ARG1 (r1)": "uid_t *euid", "ARG2 (r2)": "uid_t *suid", "ARG3 (r3)": "-", "ARG4 (r4)": "-", "ARG5 (r5)": "-"}, "166": {"NR": "166", "SYSCALL NAME": "not implemented", "references": "", "r7": "A6", "ARG0 (r0)": "", "ARG1 (r1)": "", "ARG2 (r2)": "", "ARG3 (r3)": "", "ARG4 (r4)": "", "ARG5 (r5)": ""}, "167": {"NR": "167", "SYSCALL NAME": "not implemented", "references": "", "r7": "A7", "ARG0 (r0)": "", "ARG1 (r1)": "", "ARG2 (r2)": "", "ARG3 (r3)": "", "ARG4 (r4)": "", "ARG5 (r5)": ""}, "168": {"NR": "168", "SYSCALL NAME": "poll", "references": "man/ cs/", "r7": "A8", "ARG0 (r0)": "struct pollfd *ufds", "ARG1 (r1)": "unsigned int nfds", "ARG2 (r2)": "int timeout", "ARG3 (r3)": "-", "ARG4 (r4)": "-", "ARG5 (r5)": "-"}, "169": {"NR": "169", "SYSCALL NAME": "nfsservctl", "references": "man/ cs/", "r7": "A9", "ARG0 (r0)": "?", "ARG1 (r1)": "?", "ARG2 (r2)": "?", "ARG3 (r3)": "?", "ARG4 (r4)": "?", "ARG5 (r5)": "?"}, "170": {"NR": "170", "SYSCALL NAME": "setresgid", "references": "man/ cs/", "r7": "AA", "ARG0 (r0)": "gid_t rgid", "ARG1 (r1)": "gid_t egid", "ARG2 (r2)": "gid_t sgid", "ARG3 (r3)": "-", "ARG4 (r4)": "-", "ARG5 (r5)": "-"}, "171": {"NR": "171", "SYSCALL NAME": "getresgid", "references": "man/ cs/", "r7": "AB", "ARG0 (r0)": "gid_t *rgid", "ARG1 (r1)": "gid_t *egid", "ARG2 (r2)": "gid_t *sgid", "ARG3 (r3)": "-", "ARG4 (r4)": "-", "ARG5 (r5)": "-"}, "172": {"NR": "172", "SYSCALL NAME": "prctl", "references": "man/ cs/", "r7": "AC", "ARG0 (r0)": "int option", "ARG1 (r1)": "unsigned long arg2", "ARG2 (r2)": "unsigned long arg3", "ARG3 (r3)": "unsigned long arg4", "ARG4 (r4)": "unsigned long arg5", "ARG5 (r5)": "-"}, "173": {"NR": "173", "SYSCALL NAME": "rt_sigreturn", "references": "man/ cs/", "r7": "AD", "ARG0 (r0)": "?", "ARG1 (r1)": "?", "ARG2 (r2)": "?", "ARG3 (r3)": "?", "ARG4 (r4)": "?", "ARG5 (r5)": "?"}, "174": {"NR": "174", "SYSCALL NAME": "rt_sigaction", "references": "man/ cs/", "r7": "AE", "ARG0 (r0)": "int", "ARG1 (r1)": "const struct sigaction *", "ARG2 (r2)": "struct sigaction *", "ARG3 (r3)": "size_t", "ARG4 (r4)": "-", "ARG5 (r5)": "-"}, "175": {"NR": "175", "SYSCALL NAME": "rt_sigprocmask", "references": "man/ cs/", "r7": "AF", "ARG0 (r0)": "int how", "ARG1 (r1)": "sigset_t *set", "ARG2 (r2)": "sigset_t *oset", "ARG3 (r3)": "size_t sigsetsize", "ARG4 (r4)": "-", "ARG5 (r5)": "-"}, "176": {"NR": "176", "SYSCALL NAME": "rt_sigpending", "references": "man/ cs/", "r7": "B0", "ARG0 (r0)": "sigset_t *set", "ARG1 (r1)": "size_t sigsetsize", "ARG2 (r2)": "-", "ARG3 (r3)": "-", "ARG4 (r4)": "-", "ARG5 (r5)": "-"}, "177": {"NR": "177", "SYSCALL NAME": "rt_sigtimedwait", "references": "man/ cs/", "r7": "B1", "ARG0 (r0)": "const sigset_t *uthese", "ARG1 (r1)": "siginfo_t *uinfo", "ARG2 (r2)": "const struct __kernel_timespec *uts", "ARG3 (r3)": "size_t sigsetsize", "ARG4 (r4)": "-", "ARG5 (r5)": "-"}, "178": {"NR": "178", "SYSCALL NAME": "rt_sigqueueinfo", "references": "man/ cs/", "r7": "B2", "ARG0 (r0)": "pid_t pid", "ARG1 (r1)": "int sig", "ARG2 (r2)": "siginfo_t *uinfo", "ARG3 (r3)": "-", "ARG4 (r4)": "-", "ARG5 (r5)": "-"}, "179": {"NR": "179", "SYSCALL NAME": "rt_sigsuspend", "references": "man/ cs/", "r7": "B3", "ARG0 (r0)": "sigset_t *unewset", "ARG1 (r1)": "size_t sigsetsize", "ARG2 (r2)": "-", "ARG3 (r3)": "-", "ARG4 (r4)": "-", "ARG5 (r5)": "-"}, "180": {"NR": "180", "SYSCALL NAME": "pread64", "references": "man/ cs/", "r7": "B4", "ARG0 (r0)": "unsigned int fd", "ARG1 (r1)": "char *buf", "ARG2 (r2)": "size_t count", "ARG3 (r3)": "loff_t pos", "ARG4 (r4)": "-", "ARG5 (r5)": "-"}, "181": {"NR": "181", "SYSCALL NAME": "pwrite64", "references": "man/ cs/", "r7": "B5", "ARG0 (r0)": "unsigned int fd", "ARG1 (r1)": "const char *buf", "ARG2 (r2)": "size_t count", "ARG3 (r3)": "loff_t pos", "ARG4 (r4)": "-", "ARG5 (r5)": "-"}, "182": {"NR": "182", "SYSCALL NAME": "chown", "references": "man/ cs/", "r7": "B6", "ARG0 (r0)": "const char *filename", "ARG1 (r1)": "uid_t user", "ARG2 (r2)": "gid_t group", "ARG3 (r3)": "-", "ARG4 (r4)": "-", "ARG5 (r5)": "-"}, "183": {"NR": "183", "SYSCALL NAME": "getcwd", "references": "man/ cs/", "r7": "B7", "ARG0 (r0)": "char *buf", "ARG1 (r1)": "unsigned long size", "ARG2 (r2)": "-", "ARG3 (r3)": "-", "ARG4 (r4)": "-", "ARG5 (r5)": "-"}, "184": {"NR": "184", "SYSCALL NAME": "capget", "references": "man/ cs/", "r7": "B8", "ARG0 (r0)": "cap_user_header_t header", "ARG1 (r1)": "cap_user_data_t dataptr", "ARG2 (r2)": "-", "ARG3 (r3)": "-", "ARG4 (r4)": "-", "ARG5 (r5)": "-"}, "185": {"NR": "185", "SYSCALL NAME": "capset", "references": "man/ cs/", "r7": "B9", "ARG0 (r0)": "cap_user_header_t header", "ARG1 (r1)": "const cap_user_data_t data", "ARG2 (r2)": "-", "ARG3 (r3)": "-", "ARG4 (r4)": "-", "ARG5 (r5)": "-"}, "186": {"NR": "186", "SYSCALL NAME": "sigaltstack", "references": "man/ cs/", "r7": "BA", "ARG0 (r0)": "const struct sigaltstack *uss", "ARG1 (r1)": "struct sigaltstack *uoss", "ARG2 (r2)": "-", "ARG3 (r3)": "-", "ARG4 (r4)": "-", "ARG5 (r5)": "-"}, "187": {"NR": "187", "SYSCALL NAME": "sendfile", "references": "man/ cs/", "r7": "BB", "ARG0 (r0)": "int out_fd", "ARG1 (r1)": "int in_fd", "ARG2 (r2)": "off_t *offset", "ARG3 (r3)": "size_t count", "ARG4 (r4)": "-", "ARG5 (r5)": "-"}, "188": {"NR": "188", "SYSCALL NAME": "not implemented", "references": "", "r7": "BC", "ARG0 (r0)": "", "ARG1 (r1)": "", "ARG2 (r2)": "", "ARG3 (r3)": "", "ARG4 (r4)": "", "ARG5 (r5)": ""}, "189": {"NR": "189", "SYSCALL NAME": "not implemented", "references": "", "r7": "BD", "ARG0 (r0)": "", "ARG1 (r1)": "", "ARG2 (r2)": "", "ARG3 (r3)": "", "ARG4 (r4)": "", "ARG5 (r5)": ""}, "190": {"NR": "190", "SYSCALL NAME": "vfork", "references": "man/ cs/", "r7": "BE", "ARG0 (r0)": "-", "ARG1 (r1)": "-", "ARG2 (r2)": "-", "ARG3 (r3)": "-", "ARG4 (r4)": "-", "ARG5 (r5)": "-"}, "191": {"NR": "191", "SYSCALL NAME": "ugetrlimit", "references": "man/ cs/", "r7": "BF", "ARG0 (r0)": "?", "ARG1 (r1)": "?", "ARG2 (r2)": "?", "ARG3 (r3)": "?", "ARG4 (r4)": "?", "ARG5 (r5)": "?"}, "192": {"NR": "192", "SYSCALL NAME": "mmap2", "references": "man/ cs/", "r7": "C0", "ARG0 (r0)": "?", "ARG1 (r1)": "?", "ARG2 (r2)": "?", "ARG3 (r3)": "?", "ARG4 (r4)": "?", "ARG5 (r5)": "?"}, "193": {"NR": "193", "SYSCALL NAME": "truncate64", "references": "man/ cs/", "r7": "C1", "ARG0 (r0)": "const char *path", "ARG1 (r1)": "loff_t length", "ARG2 (r2)": "-", "ARG3 (r3)": "-", "ARG4 (r4)": "-", "ARG5 (r5)": "-"}, "194": {"NR": "194", "SYSCALL NAME": "ftruncate64", "references": "man/ cs/", "r7": "C2", "ARG0 (r0)": "unsigned int fd", "ARG1 (r1)": "loff_t length", "ARG2 (r2)": "-", "ARG3 (r3)": "-", "ARG4 (r4)": "-", "ARG5 (r5)": "-"}, "195": {"NR": "195", "SYSCALL NAME": "stat64", "references": "man/ cs/", "r7": "C3", "ARG0 (r0)": "const char *filename", "ARG1 (r1)": "struct stat64 *statbuf", "ARG2 (r2)": "-", "ARG3 (r3)": "-", "ARG4 (r4)": "-", "ARG5 (r5)": "-"}, "196": {"NR": "196", "SYSCALL NAME": "lstat64", "references": "man/ cs/", "r7": "C4", "ARG0 (r0)": "const char *filename", "ARG1 (r1)": "struct stat64 *statbuf", "ARG2 (r2)": "-", "ARG3 (r3)": "-", "ARG4 (r4)": "-", "ARG5 (r5)": "-"}, "197": {"NR": "197", "SYSCALL NAME": "fstat64", "references": "man/ cs/", "r7": "C5", "ARG0 (r0)": "unsigned long fd", "ARG1 (r1)": "struct stat64 *statbuf", "ARG2 (r2)": "-", "ARG3 (r3)": "-", "ARG4 (r4)": "-", "ARG5 (r5)": "-"}, "198": {"NR": "198", "SYSCALL NAME": "lchown32", "references": "man/ cs/", "r7": "C6", "ARG0 (r0)": "?", "ARG1 (r1)": "?", "ARG2 (r2)": "?", "ARG3 (r3)": "?", "ARG4 (r4)": "?", "ARG5 (r5)": "?"}, "199": {"NR": "199", "SYSCALL NAME": "getuid32", "references": "man/ cs/", "r7": "C7", "ARG0 (r0)": "?", "ARG1 (r1)": "?", "ARG2 (r2)": "?", "ARG3 (r3)": "?", "ARG4 (r4)": "?", "ARG5 (r5)": "?"}, "200": {"NR": "200", "SYSCALL NAME": "getgid32", "references": "man/ cs/", "r7": "C8", "ARG0 (r0)": "?", "ARG1 (r1)": "?", "ARG2 (r2)": "?", "ARG3 (r3)": "?", "ARG4 (r4)": "?", "ARG5 (r5)": "?"}, "201": {"NR": "201", "SYSCALL NAME": "geteuid32", "references": "man/ cs/", "r7": "C9", "ARG0 (r0)": "?", "ARG1 (r1)": "?", "ARG2 (r2)": "?", "ARG3 (r3)": "?", "ARG4 (r4)": "?", "ARG5 (r5)": "?"}, "202": {"NR": "202", "SYSCALL NAME": "getegid32", "references": "man/ cs/", "r7": "CA", "ARG0 (r0)": "?", "ARG1 (r1)": "?", "ARG2 (r2)": "?", "ARG3 (r3)": "?", "ARG4 (r4)": "?", "ARG5 (r5)": "?"}, "203": {"NR": "203", "SYSCALL NAME": "setreuid32", "references": "man/ cs/", "r7": "CB", "ARG0 (r0)": "?", "ARG1 (r1)": "?", "ARG2 (r2)": "?", "ARG3 (r3)": "?", "ARG4 (r4)": "?", "ARG5 (r5)": "?"}, "204": {"NR": "204", "SYSCALL NAME": "setregid32", "references": "man/ cs/", "r7": "CC", "ARG0 (r0)": "?", "ARG1 (r1)": "?", "ARG2 (r2)": "?", "ARG3 (r3)": "?", "ARG4 (r4)": "?", "ARG5 (r5)": "?"}, "205": {"NR": "205", "SYSCALL NAME": "getgroups32", "references": "man/ cs/", "r7": "CD", "ARG0 (r0)": "?", "ARG1 (r1)": "?", "ARG2 (r2)": "?", "ARG3 (r3)": "?", "ARG4 (r4)": "?", "ARG5 (r5)": "?"}, "206": {"NR": "206", "SYSCALL NAME": "setgroups32", "references": "man/ cs/", "r7": "CE", "ARG0 (r0)": "?", "ARG1 (r1)": "?", "ARG2 (r2)": "?", "ARG3 (r3)": "?", "ARG4 (r4)": "?", "ARG5 (r5)": "?"}, "207": {"NR": "207", "SYSCALL NAME": "fchown32", "references": "man/ cs/", "r7": "CF", "ARG0 (r0)": "?", "ARG1 (r1)": "?", "ARG2 (r2)": "?", "ARG3 (r3)": "?", "ARG4 (r4)": "?", "ARG5 (r5)": "?"}, "208": {"NR": "208", "SYSCALL NAME": "setresuid32", "references": "man/ cs/", "r7": "D0", "ARG0 (r0)": "?", "ARG1 (r1)": "?", "ARG2 (r2)": "?", "ARG3 (r3)": "?", "ARG4 (r4)": "?", "ARG5 (r5)": "?"}, "209": {"NR": "209", "SYSCALL NAME": "getresuid32", "references": "man/ cs/", "r7": "D1", "ARG0 (r0)": "?", "ARG1 (r1)": "?", "ARG2 (r2)": "?", "ARG3 (r3)": "?", "ARG4 (r4)": "?", "ARG5 (r5)": "?"}, "210": {"NR": "210", "SYSCALL NAME": "setresgid32", "references": "man/ cs/", "r7": "D2", "ARG0 (r0)": "?", "ARG1 (r1)": "?", "ARG2 (r2)": "?", "ARG3 (r3)": "?", "ARG4 (r4)": "?", "ARG5 (r5)": "?"}, "211": {"NR": "211", "SYSCALL NAME": "getresgid32", "references": "man/ cs/", "r7": "D3", "ARG0 (r0)": "?", "ARG1 (r1)": "?", "ARG2 (r2)": "?", "ARG3 (r3)": "?", "ARG4 (r4)": "?", "ARG5 (r5)": "?"}, "212": {"NR": "212", "SYSCALL NAME": "chown32", "references": "man/ cs/", "r7": "D4", "ARG0 (r0)": "?", "ARG1 (r1)": "?", "ARG2 (r2)": "?", "ARG3 (r3)": "?", "ARG4 (r4)": "?", "ARG5 (r5)": "?"}, "213": {"NR": "213", "SYSCALL NAME": "setuid32", "references": "man/ cs/", "r7": "D5", "ARG0 (r0)": "?", "ARG1 (r1)": "?", "ARG2 (r2)": "?", "ARG3 (r3)": "?", "ARG4 (r4)": "?", "ARG5 (r5)": "?"}, "214": {"NR": "214", "SYSCALL NAME": "setgid32", "references": "man/ cs/", "r7": "D6", "ARG0 (r0)": "?", "ARG1 (r1)": "?", "ARG2 (r2)": "?", "ARG3 (r3)": "?", "ARG4 (r4)": "?", "ARG5 (r5)": "?"}, "215": {"NR": "215", "SYSCALL NAME": "setfsuid32", "references": "man/ cs/", "r7": "D7", "ARG0 (r0)": "?", "ARG1 (r1)": "?", "ARG2 (r2)": "?", "ARG3 (r3)": "?", "ARG4 (r4)": "?", "ARG5 (r5)": "?"}, "216": {"NR": "216", "SYSCALL NAME": "setfsgid32", "references": "man/ cs/", "r7": "D8", "ARG0 (r0)": "?", "ARG1 (r1)": "?", "ARG2 (r2)": "?", "ARG3 (r3)": "?", "ARG4 (r4)": "?", "ARG5 (r5)": "?"}, "217": {"NR": "217", "SYSCALL NAME": "getdents64", "references": "man/ cs/", "r7": "D9", "ARG0 (r0)": "unsigned int fd", "ARG1 (r1)": "struct linux_dirent64 *dirent", "ARG2 (r2)": "unsigned int count", "ARG3 (r3)": "-", "ARG4 (r4)": "-", "ARG5 (r5)": "-"}, "218": {"NR": "218", "SYSCALL NAME": "pivot_root", "references": "man/ cs/", "r7": "DA", "ARG0 (r0)": "const char *new_root", "ARG1 (r1)": "const char *put_old", "ARG2 (r2)": "-", "ARG3 (r3)": "-", "ARG4 (r4)": "-", "ARG5 (r5)": "-"}, "219": {"NR": "219", "SYSCALL NAME": "mincore", "references": "man/ cs/", "r7": "DB", "ARG0 (r0)": "unsigned long start", "ARG1 (r1)": "size_t len", "ARG2 (r2)": "unsigned char * vec", "ARG3 (r3)": "-", "ARG4 (r4)": "-", "ARG5 (r5)": "-"}, "220": {"NR": "220", "SYSCALL NAME": "madvise", "references": "man/ cs/", "r7": "DC", "ARG0 (r0)": "unsigned long start", "ARG1 (r1)": "size_t len", "ARG2 (r2)": "int behavior", "ARG3 (r3)": "-", "ARG4 (r4)": "-", "ARG5 (r5)": "-"}, "221": {"NR": "221", "SYSCALL NAME": "fcntl64", "references": "man/ cs/", "r7": "DD", "ARG0 (r0)": "unsigned int fd", "ARG1 (r1)": "unsigned int cmd", "ARG2 (r2)": "unsigned long arg", "ARG3 (r3)": "-", "ARG4 (r4)": "-", "ARG5 (r5)": "-"}, "222": {"NR": "222", "SYSCALL NAME": "not implemented", "references": "", "r7": "DE", "ARG0 (r0)": "", "ARG1 (r1)": "", "ARG2 (r2)": "", "ARG3 (r3)": "", "ARG4 (r4)": "", "ARG5 (r5)": ""}, "223": {"NR": "223", "SYSCALL NAME": "not implemented", "references": "", "r7": "DF", "ARG0 (r0)": "", "ARG1 (r1)": "", "ARG2 (r2)": "", "ARG3 (r3)": "", "ARG4 (r4)": "", "ARG5 (r5)": ""}, "224": {"NR": "224", "SYSCALL NAME": "gettid", "references": "man/ cs/", "r7": "E0", "ARG0 (r0)": "-", "ARG1 (r1)": "-", "ARG2 (r2)": "-", "ARG3 (r3)": "-", "ARG4 (r4)": "-", "ARG5 (r5)": "-"}, "225": {"NR": "225", "SYSCALL NAME": "readahead", "references": "man/ cs/", "r7": "E1", "ARG0 (r0)": "int fd", "ARG1 (r1)": "loff_t offset", "ARG2 (r2)": "size_t count", "ARG3 (r3)": "-", "ARG4 (r4)": "-", "ARG5 (r5)": "-"}, "226": {"NR": "226", "SYSCALL NAME": "setxattr", "references": "man/ cs/", "r7": "E2", "ARG0 (r0)": "const char *path", "ARG1 (r1)": "const char *name", "ARG2 (r2)": "const void *value", "ARG3 (r3)": "size_t size", "ARG4 (r4)": "int flags", "ARG5 (r5)": "-"}, "227": {"NR": "227", "SYSCALL NAME": "lsetxattr", "references": "man/ cs/", "r7": "E3", "ARG0 (r0)": "const char *path", "ARG1 (r1)": "const char *name", "ARG2 (r2)": "const void *value", "ARG3 (r3)": "size_t size", "ARG4 (r4)": "int flags", "ARG5 (r5)": "-"}, "228": {"NR": "228", "SYSCALL NAME": "fsetxattr", "references": "man/ cs/", "r7": "E4", "ARG0 (r0)": "int fd", "ARG1 (r1)": "const char *name", "ARG2 (r2)": "const void *value", "ARG3 (r3)": "size_t size", "ARG4 (r4)": "int flags", "ARG5 (r5)": "-"}, "229": {"NR": "229", "SYSCALL NAME": "getxattr", "references": "man/ cs/", "r7": "E5", "ARG0 (r0)": "const char *path", "ARG1 (r1)": "const char *name", "ARG2 (r2)": "void *value", "ARG3 (r3)": "size_t size", "ARG4 (r4)": "-", "ARG5 (r5)": "-"}, "230": {"NR": "230", "SYSCALL NAME": "lgetxattr", "references": "man/ cs/", "r7": "E6", "ARG0 (r0)": "const char *path", "ARG1 (r1)": "const char *name", "ARG2 (r2)": "void *value", "ARG3 (r3)": "size_t size", "ARG4 (r4)": "-", "ARG5 (r5)": "-"}, "231": {"NR": "231", "SYSCALL NAME": "fgetxattr", "references": "man/ cs/", "r7": "E7", "ARG0 (r0)": "int fd", "ARG1 (r1)": "const char *name", "ARG2 (r2)": "void *value", "ARG3 (r3)": "size_t size", "ARG4 (r4)": "-", "ARG5 (r5)": "-"}, "232": {"NR": "232", "SYSCALL NAME": "listxattr", "references": "man/ cs/", "r7": "E8", "ARG0 (r0)": "const char *path", "ARG1 (r1)": "char *list", "ARG2 (r2)": "size_t size", "ARG3 (r3)": "-", "ARG4 (r4)": "-", "ARG5 (r5)": "-"}, "233": {"NR": "233", "SYSCALL NAME": "llistxattr", "references": "man/ cs/", "r7": "E9", "ARG0 (r0)": "const char *path", "ARG1 (r1)": "char *list", "ARG2 (r2)": "size_t size", "ARG3 (r3)": "-", "ARG4 (r4)": "-", "ARG5 (r5)": "-"}, "234": {"NR": "234", "SYSCALL NAME": "flistxattr", "references": "man/ cs/", "r7": "EA", "ARG0 (r0)": "int fd", "ARG1 (r1)": "char *list", "ARG2 (r2)": "size_t size", "ARG3 (r3)": "-", "ARG4 (r4)": "-", "ARG5 (r5)": "-"}, "235": {"NR": "235", "SYSCALL NAME": "removexattr", "references": "man/ cs/", "r7": "EB", "ARG0 (r0)": "const char *path", "ARG1 (r1)": "const char *name", "ARG2 (r2)": "-", "ARG3 (r3)": "-", "ARG4 (r4)": "-", "ARG5 (r5)": "-"}, "236": {"NR": "236", "SYSCALL NAME": "lremovexattr", "references": "man/ cs/", "r7": "EC", "ARG0 (r0)": "const char *path", "ARG1 (r1)": "const char *name", "ARG2 (r2)": "-", "ARG3 (r3)": "-", "ARG4 (r4)": "-", "ARG5 (r5)": "-"}, "237": {"NR": "237", "SYSCALL NAME": "fremovexattr", "references": "man/ cs/", "r7": "ED", "ARG0 (r0)": "int fd", "ARG1 (r1)": "const char *name", "ARG2 (r2)": "-", "ARG3 (r3)": "-", "ARG4 (r4)": "-", "ARG5 (r5)": "-"}, "238": {"NR": "238", "SYSCALL NAME": "tkill", "references": "man/ cs/", "r7": "EE", "ARG0 (r0)": "pid_t pid", "ARG1 (r1)": "int sig", "ARG2 (r2)": "-", "ARG3 (r3)": "-", "ARG4 (r4)": "-", "ARG5 (r5)": "-"}, "239": {"NR": "239", "SYSCALL NAME": "sendfile64", "references": "man/ cs/", "r7": "EF", "ARG0 (r0)": "int out_fd", "ARG1 (r1)": "int in_fd", "ARG2 (r2)": "loff_t *offset", "ARG3 (r3)": "size_t count", "ARG4 (r4)": "-", "ARG5 (r5)": "-"}, "240": {"NR": "240", "SYSCALL NAME": "futex", "references": "man/ cs/", "r7": "F0", "ARG0 (r0)": "u32 *uaddr", "ARG1 (r1)": "int op", "ARG2 (r2)": "u32 val", "ARG3 (r3)": "struct __kernel_timespec *utime", "ARG4 (r4)": "u32 *uaddr2", "ARG5 (r5)": "u32 val3"}, "241": {"NR": "241", "SYSCALL NAME": "sched_setaffinity", "references": "man/ cs/", "r7": "F1", "ARG0 (r0)": "pid_t pid", "ARG1 (r1)": "unsigned int len", "ARG2 (r2)": "unsigned long *user_mask_ptr", "ARG3 (r3)": "-", "ARG4 (r4)": "-", "ARG5 (r5)": "-"}, "242": {"NR": "242", "SYSCALL NAME": "sched_getaffinity", "references": "man/ cs/", "r7": "F2", "ARG0 (r0)": "pid_t pid", "ARG1 (r1)": "unsigned int len", "ARG2 (r2)": "unsigned long *user_mask_ptr", "ARG3 (r3)": "-", "ARG4 (r4)": "-", "ARG5 (r5)": "-"}, "243": {"NR": "243", "SYSCALL NAME": "io_setup", "references": "man/ cs/", "r7": "F3", "ARG0 (r0)": "unsigned nr_reqs", "ARG1 (r1)": "aio_context_t *ctx", "ARG2 (r2)": "-", "ARG3 (r3)": "-", "ARG4 (r4)": "-", "ARG5 (r5)": "-"}, "244": {"NR": "244", "SYSCALL NAME": "io_destroy", "references": "man/ cs/", "r7": "F4", "ARG0 (r0)": "aio_context_t ctx", "ARG1 (r1)": "-", "ARG2 (r2)": "-", "ARG3 (r3)": "-", "ARG4 (r4)": "-", "ARG5 (r5)": "-"}, "245": {"NR": "245", "SYSCALL NAME": "io_getevents", "references": "man/ cs/", "r7": "F5", "ARG0 (r0)": "aio_context_t ctx_id", "ARG1 (r1)": "long min_nr", "ARG2 (r2)": "long nr", "ARG3 (r3)": "struct io_event *events", "ARG4 (r4)": "struct __kernel_timespec *timeout", "ARG5 (r5)": "-"}, "246": {"NR": "246", "SYSCALL NAME": "io_submit", "references": "man/ cs/", "r7": "F6", "ARG0 (r0)": "aio_context_t", "ARG1 (r1)": "long", "ARG2 (r2)": "struct iocb * *", "ARG3 (r3)": "-", "ARG4 (r4)": "-", "ARG5 (r5)": "-"}, "247": {"NR": "247", "SYSCALL NAME": "io_cancel", "references": "man/ cs/", "r7": "F7", "ARG0 (r0)": "aio_context_t ctx_id", "ARG1 (r1)": "struct iocb *iocb", "ARG2 (r2)": "struct io_event *result", "ARG3 (r3)": "-", "ARG4 (r4)": "-", "ARG5 (r5)": "-"}, "248": {"NR": "248", "SYSCALL NAME": "exit_group", "references": "man/ cs/", "r7": "F8", "ARG0 (r0)": "int error_code", "ARG1 (r1)": "-", "ARG2 (r2)": "-", "ARG3 (r3)": "-", "ARG4 (r4)": "-", "ARG5 (r5)": "-"}, "249": {"NR": "249", "SYSCALL NAME": "lookup_dcookie", "references": "man/ cs/", "r7": "F9", "ARG0 (r0)": "u64 cookie64", "ARG1 (r1)": "char *buf", "ARG2 (r2)": "size_t len", "ARG3 (r3)": "-", "ARG4 (r4)": "-", "ARG5 (r5)": "-"}, "250": {"NR": "250", "SYSCALL NAME": "epoll_create", "references": "man/ cs/", "r7": "FA", "ARG0 (r0)": "int size", "ARG1 (r1)": "-", "ARG2 (r2)": "-", "ARG3 (r3)": "-", "ARG4 (r4)": "-", "ARG5 (r5)": "-"}, "251": {"NR": "251", "SYSCALL NAME": "epoll_ctl", "references": "man/ cs/", "r7": "FB", "ARG0 (r0)": "int epfd", "ARG1 (r1)": "int op", "ARG2 (r2)": "int fd", "ARG3 (r3)": "struct epoll_event *event", "ARG4 (r4)": "-", "ARG5 (r5)": "-"}, "252": {"NR": "252", "SYSCALL NAME": "epoll_wait", "references": "man/ cs/", "r7": "FC", "ARG0 (r0)": "int epfd", "ARG1 (r1)": "struct epoll_event *events", "ARG2 (r2)": "int maxevents", "ARG3 (r3)": "int timeout", "ARG4 (r4)": "-", "ARG5 (r5)": "-"}, "253": {"NR": "253", "SYSCALL NAME": "remap_file_pages", "references": "man/ cs/", "r7": "FD", "ARG0 (r0)": "unsigned long start", "ARG1 (r1)": "unsigned long size", "ARG2 (r2)": "unsigned long prot", "ARG3 (r3)": "unsigned long pgoff", "ARG4 (r4)": "unsigned long flags", "ARG5 (r5)": "-"}, "254": {"NR": "254", "SYSCALL NAME": "not implemented", "references": "", "r7": "FE", "ARG0 (r0)": "", "ARG1 (r1)": "", "ARG2 (r2)": "", "ARG3 (r3)": "", "ARG4 (r4)": "", "ARG5 (r5)": ""}, "255": {"NR": "255", "SYSCALL NAME": "not implemented", "references": "", "r7": "FF", "ARG0 (r0)": "", "ARG1 (r1)": "", "ARG2 (r2)": "", "ARG3 (r3)": "", "ARG4 (r4)": "", "ARG5 (r5)": ""}, "256": {"NR": "256", "SYSCALL NAME": "set_tid_address", "references": "man/ cs/", "r7": "100", "ARG0 (r0)": "int *tidptr", "ARG1 (r1)": "-", "ARG2 (r2)": "-", "ARG3 (r3)": "-", "ARG4 (r4)": "-", "ARG5 (r5)": "-"}, "257": {"NR": "257", "SYSCALL NAME": "timer_create", "references": "man/ cs/", "r7": "101", "ARG0 (r0)": "clockid_t which_clock", "ARG1 (r1)": "struct sigevent *timer_event_spec", "ARG2 (r2)": "timer_t * created_timer_id", "ARG3 (r3)": "-", "ARG4 (r4)": "-", "ARG5 (r5)": "-"}, "258": {"NR": "258", "SYSCALL NAME": "timer_settime", "references": "man/ cs/", "r7": "102", "ARG0 (r0)": "timer_t timer_id", "ARG1 (r1)": "int flags", "ARG2 (r2)": "const struct __kernel_itimerspec *new_setting", "ARG3 (r3)": "struct __kernel_itimerspec *old_setting", "ARG4 (r4)": "-", "ARG5 (r5)": "-"}, "259": {"NR": "259", "SYSCALL NAME": "timer_gettime", "references": "man/ cs/", "r7": "103", "ARG0 (r0)": "timer_t timer_id", "ARG1 (r1)": "struct __kernel_itimerspec *setting", "ARG2 (r2)": "-", "ARG3 (r3)": "-", "ARG4 (r4)": "-", "ARG5 (r5)": "-"}, "260": {"NR": "260", "SYSCALL NAME": "timer_getoverrun", "references": "man/ cs/", "r7": "104", "ARG0 (r0)": "timer_t timer_id", "ARG1 (r1)": "-", "ARG2 (r2)": "-", "ARG3 (r3)": "-", "ARG4 (r4)": "-", "ARG5 (r5)": "-"}, "261": {"NR": "261", "SYSCALL NAME": "timer_delete", "references": "man/ cs/", "r7": "105", "ARG0 (r0)": "timer_t timer_id", "ARG1 (r1)": "-", "ARG2 (r2)": "-", "ARG3 (r3)": "-", "ARG4 (r4)": "-", "ARG5 (r5)": "-"}, "262": {"NR": "262", "SYSCALL NAME": "clock_settime", "references": "man/ cs/", "r7": "106", "ARG0 (r0)": "clockid_t which_clock", "ARG1 (r1)": "const struct __kernel_timespec *tp", "ARG2 (r2)": "-", "ARG3 (r3)": "-", "ARG4 (r4)": "-", "ARG5 (r5)": "-"}, "263": {"NR": "263", "SYSCALL NAME": "clock_gettime", "references": "man/ cs/", "r7": "107", "ARG0 (r0)": "clockid_t which_clock", "ARG1 (r1)": "struct __kernel_timespec *tp", "ARG2 (r2)": "-", "ARG3 (r3)": "-", "ARG4 (r4)": "-", "ARG5 (r5)": "-"}, "264": {"NR": "264", "SYSCALL NAME": "clock_getres", "references": "man/ cs/", "r7": "108", "ARG0 (r0)": "clockid_t which_clock", "ARG1 (r1)": "struct __kernel_timespec *tp", "ARG2 (r2)": "-", "ARG3 (r3)": "-", "ARG4 (r4)": "-", "ARG5 (r5)": "-"}, "265": {"NR": "265", "SYSCALL NAME": "clock_nanosleep", "references": "man/ cs/", "r7": "109", "ARG0 (r0)": "clockid_t which_clock", "ARG1 (r1)": "int flags", "ARG2 (r2)": "const struct __kernel_timespec *rqtp", "ARG3 (r3)": "struct __kernel_timespec *rmtp", "ARG4 (r4)": "-", "ARG5 (r5)": "-"}, "266": {"NR": "266", "SYSCALL NAME": "statfs64", "references": "man/ cs/", "r7": "10A", "ARG0 (r0)": "const char *path", "ARG1 (r1)": "size_t sz", "ARG2 (r2)": "struct statfs64 *buf", "ARG3 (r3)": "-", "ARG4 (r4)": "-", "ARG5 (r5)": "-"}, "267": {"NR": "267", "SYSCALL NAME": "fstatfs64", "references": "man/ cs/", "r7": "10B", "ARG0 (r0)": "unsigned int fd", "ARG1 (r1)": "size_t sz", "ARG2 (r2)": "struct statfs64 *buf", "ARG3 (r3)": "-", "ARG4 (r4)": "-", "ARG5 (r5)": "-"}, "268": {"NR": "268", "SYSCALL NAME": "tgkill", "references": "man/ cs/", "r7": "10C", "ARG0 (r0)": "pid_t tgid", "ARG1 (r1)": "pid_t pid", "ARG2 (r2)": "int sig", "ARG3 (r3)": "-", "ARG4 (r4)": "-", "ARG5 (r5)": "-"}, "269": {"NR": "269", "SYSCALL NAME": "utimes", "references": "man/ cs/", "r7": "10D", "ARG0 (r0)": "char *filename", "ARG1 (r1)": "struct timeval *utimes", "ARG2 (r2)": "-", "ARG3 (r3)": "-", "ARG4 (r4)": "-", "ARG5 (r5)": "-"}, "270": {"NR": "270", "SYSCALL NAME": "arm_fadvise64_64", "references": "man/ cs/", "r7": "10E", "ARG0 (r0)": "?", "ARG1 (r1)": "?", "ARG2 (r2)": "?", "ARG3 (r3)": "?", "ARG4 (r4)": "?", "ARG5 (r5)": "?"}, "271": {"NR": "271", "SYSCALL NAME": "pciconfig_iobase", "references": "man/ cs/", "r7": "10F", "ARG0 (r0)": "long which", "ARG1 (r1)": "unsigned long bus", "ARG2 (r2)": "unsigned long devfn", "ARG3 (r3)": "-", "ARG4 (r4)": "-", "ARG5 (r5)": "-"}, "272": {"NR": "272", "SYSCALL NAME": "pciconfig_read", "references": "man/ cs/", "r7": "110", "ARG0 (r0)": "unsigned long bus", "ARG1 (r1)": "unsigned long dfn", "ARG2 (r2)": "unsigned long off", "ARG3 (r3)": "unsigned long len", "ARG4 (r4)": "void *buf", "ARG5 (r5)": "-"}, "273": {"NR": "273", "SYSCALL NAME": "pciconfig_write", "references": "man/ cs/", "r7": "111", "ARG0 (r0)": "unsigned long bus", "ARG1 (r1)": "unsigned long dfn", "ARG2 (r2)": "unsigned long off", "ARG3 (r3)": "unsigned long len", "ARG4 (r4)": "void *buf", "ARG5 (r5)": "-"}, "274": {"NR": "274", "SYSCALL NAME": "mq_open", "references": "man/ cs/", "r7": "112", "ARG0 (r0)": "const char *name", "ARG1 (r1)": "int oflag", "ARG2 (r2)": "umode_t mode", "ARG3 (r3)": "struct mq_attr *attr", "ARG4 (r4)": "-", "ARG5 (r5)": "-"}, "275": {"NR": "275", "SYSCALL NAME": "mq_unlink", "references": "man/ cs/", "r7": "113", "ARG0 (r0)": "const char *name", "ARG1 (r1)": "-", "ARG2 (r2)": "-", "ARG3 (r3)": "-", "ARG4 (r4)": "-", "ARG5 (r5)": "-"}, "276": {"NR": "276", "SYSCALL NAME": "mq_timedsend", "references": "man/ cs/", "r7": "114", "ARG0 (r0)": "mqd_t mqdes", "ARG1 (r1)": "const char *msg_ptr", "ARG2 (r2)": "size_t msg_len", "ARG3 (r3)": "unsigned int msg_prio", "ARG4 (r4)": "const struct __kernel_timespec *abs_timeout", "ARG5 (r5)": "-"}, "277": {"NR": "277", "SYSCALL NAME": "mq_timedreceive", "references": "man/ cs/", "r7": "115", "ARG0 (r0)": "mqd_t mqdes", "ARG1 (r1)": "char *msg_ptr", "ARG2 (r2)": "size_t msg_len", "ARG3 (r3)": "unsigned int *msg_prio", "ARG4 (r4)": "const struct __kernel_timespec *abs_timeout", "ARG5 (r5)": "-"}, "278": {"NR": "278", "SYSCALL NAME": "mq_notify", "references": "man/ cs/", "r7": "116", "ARG0 (r0)": "mqd_t mqdes", "ARG1 (r1)": "const struct sigevent *notification", "ARG2 (r2)": "-", "ARG3 (r3)": "-", "ARG4 (r4)": "-", "ARG5 (r5)": "-"}, "279": {"NR": "279", "SYSCALL NAME": "mq_getsetattr", "references": "man/ cs/", "r7": "117", "ARG0 (r0)": "mqd_t mqdes", "ARG1 (r1)": "const struct mq_attr *mqstat", "ARG2 (r2)": "struct mq_attr *omqstat", "ARG3 (r3)": "-", "ARG4 (r4)": "-", "ARG5 (r5)": "-"}, "280": {"NR": "280", "SYSCALL NAME": "waitid", "references": "man/ cs/", "r7": "118", "ARG0 (r0)": "int which", "ARG1 (r1)": "pid_t pid", "ARG2 (r2)": "struct siginfo *infop", "ARG3 (r3)": "int options", "ARG4 (r4)": "struct rusage *ru", "ARG5 (r5)": "-"}, "281": {"NR": "281", "SYSCALL NAME": "socket", "references": "man/ cs/", "r7": "119", "ARG0 (r0)": "int", "ARG1 (r1)": "int", "ARG2 (r2)": "int", "ARG3 (r3)": "-", "ARG4 (r4)": "-", "ARG5 (r5)": "-"}, "282": {"NR": "282", "SYSCALL NAME": "bind", "references": "man/ cs/", "r7": "11A", "ARG0 (r0)": "int", "ARG1 (r1)": "struct sockaddr *", "ARG2 (r2)": "int", "ARG3 (r3)": "-", "ARG4 (r4)": "-", "ARG5 (r5)": "-"}, "283": {"NR": "283", "SYSCALL NAME": "connect", "references": "man/ cs/", "r7": "11B", "ARG0 (r0)": "int", "ARG1 (r1)": "struct sockaddr *", "ARG2 (r2)": "int", "ARG3 (r3)": "-", "ARG4 (r4)": "-", "ARG5 (r5)": "-"}, "284": {"NR": "284", "SYSCALL NAME": "listen", "references": "man/ cs/", "r7": "11C", "ARG0 (r0)": "int", "ARG1 (r1)": "int", "ARG2 (r2)": "-", "ARG3 (r3)": "-", "ARG4 (r4)": "-", "ARG5 (r5)": "-"}, "285": {"NR": "285", "SYSCALL NAME": "accept", "references": "man/ cs/", "r7": "11D", "ARG0 (r0)": "int", "ARG1 (r1)": "struct sockaddr *", "ARG2 (r2)": "int *", "ARG3 (r3)": "-", "ARG4 (r4)": "-", "ARG5 (r5)": "-"}, "286": {"NR": "286", "SYSCALL NAME": "getsockname", "references": "man/ cs/", "r7": "11E", "ARG0 (r0)": "int", "ARG1 (r1)": "struct sockaddr *", "ARG2 (r2)": "int *", "ARG3 (r3)": "-", "ARG4 (r4)": "-", "ARG5 (r5)": "-"}, "287": {"NR": "287", "SYSCALL NAME": "getpeername", "references": "man/ cs/", "r7": "11F", "ARG0 (r0)": "int", "ARG1 (r1)": "struct sockaddr *", "ARG2 (r2)": "int *", "ARG3 (r3)": "-", "ARG4 (r4)": "-", "ARG5 (r5)": "-"}, "288": {"NR": "288", "SYSCALL NAME": "socketpair", "references": "man/ cs/", "r7": "120", "ARG0 (r0)": "int", "ARG1 (r1)": "int", "ARG2 (r2)": "int", "ARG3 (r3)": "int *", "ARG4 (r4)": "-", "ARG5 (r5)": "-"}, "289": {"NR": "289", "SYSCALL NAME": "send", "references": "man/ cs/", "r7": "121", "ARG0 (r0)": "int", "ARG1 (r1)": "void *", "ARG2 (r2)": "size_t", "ARG3 (r3)": "unsigned", "ARG4 (r4)": "-", "ARG5 (r5)": "-"}, "290": {"NR": "290", "SYSCALL NAME": "sendto", "references": "man/ cs/", "r7": "122", "ARG0 (r0)": "int", "ARG1 (r1)": "void *", "ARG2 (r2)": "size_t", "ARG3 (r3)": "unsigned", "ARG4 (r4)": "struct sockaddr *", "ARG5 (r5)": "int"}, "291": {"NR": "291", "SYSCALL NAME": "recv", "references": "man/ cs/", "r7": "123", "ARG0 (r0)": "int", "ARG1 (r1)": "void *", "ARG2 (r2)": "size_t", "ARG3 (r3)": "unsigned", "ARG4 (r4)": "-", "ARG5 (r5)": "-"}, "292": {"NR": "292", "SYSCALL NAME": "recvfrom", "references": "man/ cs/", "r7": "124", "ARG0 (r0)": "int", "ARG1 (r1)": "void *", "ARG2 (r2)": "size_t", "ARG3 (r3)": "unsigned", "ARG4 (r4)": "struct sockaddr *", "ARG5 (r5)": "int *"}, "293": {"NR": "293", "SYSCALL NAME": "shutdown", "references": "man/ cs/", "r7": "125", "ARG0 (r0)": "int", "ARG1 (r1)": "int", "ARG2 (r2)": "-", "ARG3 (r3)": "-", "ARG4 (r4)": "-", "ARG5 (r5)": "-"}, "294": {"NR": "294", "SYSCALL NAME": "setsockopt", "references": "man/ cs/", "r7": "126", "ARG0 (r0)": "int fd", "ARG1 (r1)": "int level", "ARG2 (r2)": "int optname", "ARG3 (r3)": "char *optval", "ARG4 (r4)": "int optlen", "ARG5 (r5)": "-"}, "295": {"NR": "295", "SYSCALL NAME": "getsockopt", "references": "man/ cs/", "r7": "127", "ARG0 (r0)": "int fd", "ARG1 (r1)": "int level", "ARG2 (r2)": "int optname", "ARG3 (r3)": "char *optval", "ARG4 (r4)": "int *optlen", "ARG5 (r5)": "-"}, "296": {"NR": "296", "SYSCALL NAME": "sendmsg", "references": "man/ cs/", "r7": "128", "ARG0 (r0)": "int fd", "ARG1 (r1)": "struct user_msghdr *msg", "ARG2 (r2)": "unsigned flags", "ARG3 (r3)": "-", "ARG4 (r4)": "-", "ARG5 (r5)": "-"}, "297": {"NR": "297", "SYSCALL NAME": "recvmsg", "references": "man/ cs/", "r7": "129", "ARG0 (r0)": "int fd", "ARG1 (r1)": "struct user_msghdr *msg", "ARG2 (r2)": "unsigned flags", "ARG3 (r3)": "-", "ARG4 (r4)": "-", "ARG5 (r5)": "-"}, "298": {"NR": "298", "SYSCALL NAME": "semop", "references": "man/ cs/", "r7": "12A", "ARG0 (r0)": "int semid", "ARG1 (r1)": "struct sembuf *sops", "ARG2 (r2)": "unsigned nsops", "ARG3 (r3)": "-", "ARG4 (r4)": "-", "ARG5 (r5)": "-"}, "299": {"NR": "299", "SYSCALL NAME": "semget", "references": "man/ cs/", "r7": "12B", "ARG0 (r0)": "key_t key", "ARG1 (r1)": "int nsems", "ARG2 (r2)": "int semflg", "ARG3 (r3)": "-", "ARG4 (r4)": "-", "ARG5 (r5)": "-"}, "300": {"NR": "300", "SYSCALL NAME": "semctl", "references": "man/ cs/", "r7": "12C", "ARG0 (r0)": "int semid", "ARG1 (r1)": "int semnum", "ARG2 (r2)": "int cmd", "ARG3 (r3)": "unsigned long arg", "ARG4 (r4)": "-", "ARG5 (r5)": "-"}, "301": {"NR": "301", "SYSCALL NAME": "msgsnd", "references": "man/ cs/", "r7": "12D", "ARG0 (r0)": "int msqid", "ARG1 (r1)": "struct msgbuf *msgp", "ARG2 (r2)": "size_t msgsz", "ARG3 (r3)": "int msgflg", "ARG4 (r4)": "-", "ARG5 (r5)": "-"}, "302": {"NR": "302", "SYSCALL NAME": "msgrcv", "references": "man/ cs/", "r7": "12E", "ARG0 (r0)": "int msqid", "ARG1 (r1)": "struct msgbuf *msgp", "ARG2 (r2)": "size_t msgsz", "ARG3 (r3)": "long msgtyp", "ARG4 (r4)": "int msgflg", "ARG5 (r5)": "-"}, "303": {"NR": "303", "SYSCALL NAME": "msgget", "references": "man/ cs/", "r7": "12F", "ARG0 (r0)": "key_t key", "ARG1 (r1)": "int msgflg", "ARG2 (r2)": "-", "ARG3 (r3)": "-", "ARG4 (r4)": "-", "ARG5 (r5)": "-"}, "304": {"NR": "304", "SYSCALL NAME": "msgctl", "references": "man/ cs/", "r7": "130", "ARG0 (r0)": "int msqid", "ARG1 (r1)": "int cmd", "ARG2 (r2)": "struct msqid_ds *buf", "ARG3 (r3)": "-", "ARG4 (r4)": "-", "ARG5 (r5)": "-"}, "305": {"NR": "305", "SYSCALL NAME": "shmat", "references": "man/ cs/", "r7": "131", "ARG0 (r0)": "int shmid", "ARG1 (r1)": "char *shmaddr", "ARG2 (r2)": "int shmflg", "ARG3 (r3)": "-", "ARG4 (r4)": "-", "ARG5 (r5)": "-"}, "306": {"NR": "306", "SYSCALL NAME": "shmdt", "references": "man/ cs/", "r7": "132", "ARG0 (r0)": "char *shmaddr", "ARG1 (r1)": "-", "ARG2 (r2)": "-", "ARG3 (r3)": "-", "ARG4 (r4)": "-", "ARG5 (r5)": "-"}, "307": {"NR": "307", "SYSCALL NAME": "shmget", "references": "man/ cs/", "r7": "133", "ARG0 (r0)": "key_t key", "ARG1 (r1)": "size_t size", "ARG2 (r2)": "int flag", "ARG3 (r3)": "-", "ARG4 (r4)": "-", "ARG5 (r5)": "-"}, "308": {"NR": "308", "SYSCALL NAME": "shmctl", "references": "man/ cs/", "r7": "134", "ARG0 (r0)": "int shmid", "ARG1 (r1)": "int cmd", "ARG2 (r2)": "struct shmid_ds *buf", "ARG3 (r3)": "-", "ARG4 (r4)": "-", "ARG5 (r5)": "-"}, "309": {"NR": "309", "SYSCALL NAME": "add_key", "references": "man/ cs/", "r7": "135", "ARG0 (r0)": "const char *_type", "ARG1 (r1)": "const char *_description", "ARG2 (r2)": "const void *_payload", "ARG3 (r3)": "size_t plen", "ARG4 (r4)": "key_serial_t destringid", "ARG5 (r5)": "-"}, "310": {"NR": "310", "SYSCALL NAME": "request_key", "references": "man/ cs/", "r7": "136", "ARG0 (r0)": "const char *_type", "ARG1 (r1)": "const char *_description", "ARG2 (r2)": "const char *_callout_info", "ARG3 (r3)": "key_serial_t destringid", "ARG4 (r4)": "-", "ARG5 (r5)": "-"}, "311": {"NR": "311", "SYSCALL NAME": "keyctl", "references": "man/ cs/", "r7": "137", "ARG0 (r0)": "int cmd", "ARG1 (r1)": "unsigned long arg2", "ARG2 (r2)": "unsigned long arg3", "ARG3 (r3)": "unsigned long arg4", "ARG4 (r4)": "unsigned long arg5", "ARG5 (r5)": "-"}, "312": {"NR": "312", "SYSCALL NAME": "semtimedop", "references": "man/ cs/", "r7": "138", "ARG0 (r0)": "int semid", "ARG1 (r1)": "struct sembuf *sops", "ARG2 (r2)": "unsigned nsops", "ARG3 (r3)": "const struct __kernel_timespec *timeout", "ARG4 (r4)": "-", "ARG5 (r5)": "-"}, "313": {"NR": "313", "SYSCALL NAME": "vserver", "references": "man/ cs/", "r7": "139", "ARG0 (r0)": "?", "ARG1 (r1)": "?", "ARG2 (r2)": "?", "ARG3 (r3)": "?", "ARG4 (r4)": "?", "ARG5 (r5)": "?"}, "314": {"NR": "314", "SYSCALL NAME": "ioprio_set", "references": "man/ cs/", "r7": "13A", "ARG0 (r0)": "int which", "ARG1 (r1)": "int who", "ARG2 (r2)": "int ioprio", "ARG3 (r3)": "-", "ARG4 (r4)": "-", "ARG5 (r5)": "-"}, "315": {"NR": "315", "SYSCALL NAME": "ioprio_get", "references": "man/ cs/", "r7": "13B", "ARG0 (r0)": "int which", "ARG1 (r1)": "int who", "ARG2 (r2)": "-", "ARG3 (r3)": "-", "ARG4 (r4)": "-", "ARG5 (r5)": "-"}, "316": {"NR": "316", "SYSCALL NAME": "inotify_init", "references": "man/ cs/", "r7": "13C", "ARG0 (r0)": "-", "ARG1 (r1)": "-", "ARG2 (r2)": "-", "ARG3 (r3)": "-", "ARG4 (r4)": "-", "ARG5 (r5)": "-"}, "317": {"NR": "317", "SYSCALL NAME": "inotify_add_watch", "references": "man/ cs/", "r7": "13D", "ARG0 (r0)": "int fd", "ARG1 (r1)": "const char *path", "ARG2 (r2)": "u32 mask", "ARG3 (r3)": "-", "ARG4 (r4)": "-", "ARG5 (r5)": "-"}, "318": {"NR": "318", "SYSCALL NAME": "inotify_rm_watch", "references": "man/ cs/", "r7": "13E", "ARG0 (r0)": "int fd", "ARG1 (r1)": "__s32 wd", "ARG2 (r2)": "-", "ARG3 (r3)": "-", "ARG4 (r4)": "-", "ARG5 (r5)": "-"}, "319": {"NR": "319", "SYSCALL NAME": "mbind", "references": "man/ cs/", "r7": "13F", "ARG0 (r0)": "unsigned long start", "ARG1 (r1)": "unsigned long len", "ARG2 (r2)": "unsigned long mode", "ARG3 (r3)": "const unsigned long *nmask", "ARG4 (r4)": "unsigned long maxnode", "ARG5 (r5)": "unsigned flags"}, "320": {"NR": "320", "SYSCALL NAME": "get_mempolicy", "references": "man/ cs/", "r7": "140", "ARG0 (r0)": "int *policy", "ARG1 (r1)": "unsigned long *nmask", "ARG2 (r2)": "unsigned long maxnode", "ARG3 (r3)": "unsigned long addr", "ARG4 (r4)": "unsigned long flags", "ARG5 (r5)": "-"}, "321": {"NR": "321", "SYSCALL NAME": "set_mempolicy", "references": "man/ cs/", "r7": "141", "ARG0 (r0)": "int mode", "ARG1 (r1)": "const unsigned long *nmask", "ARG2 (r2)": "unsigned long maxnode", "ARG3 (r3)": "-", "ARG4 (r4)": "-", "ARG5 (r5)": "-"}, "322": {"NR": "322", "SYSCALL NAME": "openat", "references": "man/ cs/", "r7": "142", "ARG0 (r0)": "int dfd", "ARG1 (r1)": "const char *filename", "ARG2 (r2)": "int flags", "ARG3 (r3)": "umode_t mode", "ARG4 (r4)": "-", "ARG5 (r5)": "-"}, "323": {"NR": "323", "SYSCALL NAME": "mkdirat", "references": "man/ cs/", "r7": "143", "ARG0 (r0)": "int dfd", "ARG1 (r1)": "const char * pathname", "ARG2 (r2)": "umode_t mode", "ARG3 (r3)": "-", "ARG4 (r4)": "-", "ARG5 (r5)": "-"}, "324": {"NR": "324", "SYSCALL NAME": "mknodat", "references": "man/ cs/", "r7": "144", "ARG0 (r0)": "int dfd", "ARG1 (r1)": "const char * filename", "ARG2 (r2)": "umode_t mode", "ARG3 (r3)": "unsigned dev", "ARG4 (r4)": "-", "ARG5 (r5)": "-"}, "325": {"NR": "325", "SYSCALL NAME": "fchownat", "references": "man/ cs/", "r7": "145", "ARG0 (r0)": "int dfd", "ARG1 (r1)": "const char *filename", "ARG2 (r2)": "uid_t user", "ARG3 (r3)": "gid_t group", "ARG4 (r4)": "int flag", "ARG5 (r5)": "-"}, "326": {"NR": "326", "SYSCALL NAME": "futimesat", "references": "man/ cs/", "r7": "146", "ARG0 (r0)": "int dfd", "ARG1 (r1)": "const char *filename", "ARG2 (r2)": "struct timeval *utimes", "ARG3 (r3)": "-", "ARG4 (r4)": "-", "ARG5 (r5)": "-"}, "327": {"NR": "327", "SYSCALL NAME": "fstatat64", "references": "man/ cs/", "r7": "147", "ARG0 (r0)": "int dfd", "ARG1 (r1)": "const char *filename", "ARG2 (r2)": "struct stat64 *statbuf", "ARG3 (r3)": "int flag", "ARG4 (r4)": "-", "ARG5 (r5)": "-"}, "328": {"NR": "328", "SYSCALL NAME": "unlinkat", "references": "man/ cs/", "r7": "148", "ARG0 (r0)": "int dfd", "ARG1 (r1)": "const char * pathname", "ARG2 (r2)": "int flag", "ARG3 (r3)": "-", "ARG4 (r4)": "-", "ARG5 (r5)": "-"}, "329": {"NR": "329", "SYSCALL NAME": "renameat", "references": "man/ cs/", "r7": "149", "ARG0 (r0)": "int olddfd", "ARG1 (r1)": "const char * oldname", "ARG2 (r2)": "int newdfd", "ARG3 (r3)": "const char * newname", "ARG4 (r4)": "-", "ARG5 (r5)": "-"}, "330": {"NR": "330", "SYSCALL NAME": "linkat", "references": "man/ cs/", "r7": "14A", "ARG0 (r0)": "int olddfd", "ARG1 (r1)": "const char *oldname", "ARG2 (r2)": "int newdfd", "ARG3 (r3)": "const char *newname", "ARG4 (r4)": "int flags", "ARG5 (r5)": "-"}, "331": {"NR": "331", "SYSCALL NAME": "symlinkat", "references": "man/ cs/", "r7": "14B", "ARG0 (r0)": "const char * oldname", "ARG1 (r1)": "int newdfd", "ARG2 (r2)": "const char * newname", "ARG3 (r3)": "-", "ARG4 (r4)": "-", "ARG5 (r5)": "-"}, "332": {"NR": "332", "SYSCALL NAME": "readlinkat", "references": "man/ cs/", "r7": "14C", "ARG0 (r0)": "int dfd", "ARG1 (r1)": "const char *path", "ARG2 (r2)": "char *buf", "ARG3 (r3)": "int bufsiz", "ARG4 (r4)": "-", "ARG5 (r5)": "-"}, "333": {"NR": "333", "SYSCALL NAME": "fchmodat", "references": "man/ cs/", "r7": "14D", "ARG0 (r0)": "int dfd", "ARG1 (r1)": "const char * filename", "ARG2 (r2)": "umode_t mode", "ARG3 (r3)": "-", "ARG4 (r4)": "-", "ARG5 (r5)": "-"}, "334": {"NR": "334", "SYSCALL NAME": "faccessat", "references": "man/ cs/", "r7": "14E", "ARG0 (r0)": "int dfd", "ARG1 (r1)": "const char *filename", "ARG2 (r2)": "int mode", "ARG3 (r3)": "-", "ARG4 (r4)": "-", "ARG5 (r5)": "-"}, "335": {"NR": "335", "SYSCALL NAME": "pselect6", "references": "man/ cs/", "r7": "14F", "ARG0 (r0)": "int", "ARG1 (r1)": "fd_set *", "ARG2 (r2)": "fd_set *", "ARG3 (r3)": "fd_set *", "ARG4 (r4)": "struct __kernel_timespec *", "ARG5 (r5)": "void *"}, "336": {"NR": "336", "SYSCALL NAME": "ppoll", "references": "man/ cs/", "r7": "150", "ARG0 (r0)": "struct pollfd *", "ARG1 (r1)": "unsigned int", "ARG2 (r2)": "struct __kernel_timespec *", "ARG3 (r3)": "const sigset_t *", "ARG4 (r4)": "size_t", "ARG5 (r5)": "-"}, "337": {"NR": "337", "SYSCALL NAME": "unshare", "references": "man/ cs/", "r7": "151", "ARG0 (r0)": "unsigned long unshare_flags", "ARG1 (r1)": "-", "ARG2 (r2)": "-", "ARG3 (r3)": "-", "ARG4 (r4)": "-", "ARG5 (r5)": "-"}, "338": {"NR": "338", "SYSCALL NAME": "set_robust_list", "references": "man/ cs/", "r7": "152", "ARG0 (r0)": "struct robust_list_head *head", "ARG1 (r1)": "size_t len", "ARG2 (r2)": "-", "ARG3 (r3)": "-", "ARG4 (r4)": "-", "ARG5 (r5)": "-"}, "339": {"NR": "339", "SYSCALL NAME": "get_robust_list", "references": "man/ cs/", "r7": "153", "ARG0 (r0)": "int pid", "ARG1 (r1)": "struct robust_list_head * *head_ptr", "ARG2 (r2)": "size_t *len_ptr", "ARG3 (r3)": "-", "ARG4 (r4)": "-", "ARG5 (r5)": "-"}, "340": {"NR": "340", "SYSCALL NAME": "splice", "references": "man/ cs/", "r7": "154", "ARG0 (r0)": "int fd_in", "ARG1 (r1)": "loff_t *off_in", "ARG2 (r2)": "int fd_out", "ARG3 (r3)": "loff_t *off_out", "ARG4 (r4)": "size_t len", "ARG5 (r5)": "unsigned int flags"}, "341": {"NR": "341", "SYSCALL NAME": "sync_file_range2", "references": "man/ cs/", "r7": "155", "ARG0 (r0)": "int fd", "ARG1 (r1)": "unsigned int flags", "ARG2 (r2)": "loff_t offset", "ARG3 (r3)": "loff_t nbytes", "ARG4 (r4)": "-", "ARG5 (r5)": "-"}, "342": {"NR": "342", "SYSCALL NAME": "tee", "references": "man/ cs/", "r7": "156", "ARG0 (r0)": "int fdin", "ARG1 (r1)": "int fdout", "ARG2 (r2)": "size_t len", "ARG3 (r3)": "unsigned int flags", "ARG4 (r4)": "-", "ARG5 (r5)": "-"}, "343": {"NR": "343", "SYSCALL NAME": "vmsplice", "references": "man/ cs/", "r7": "157", "ARG0 (r0)": "int fd", "ARG1 (r1)": "const struct iovec *iov", "ARG2 (r2)": "unsigned long nr_segs", "ARG3 (r3)": "unsigned int flags", "ARG4 (r4)": "-", "ARG5 (r5)": "-"}, "344": {"NR": "344", "SYSCALL NAME": "move_pages", "references": "man/ cs/", "r7": "158", "ARG0 (r0)": "pid_t pid", "ARG1 (r1)": "unsigned long nr_pages", "ARG2 (r2)": "const void * *pages", "ARG3 (r3)": "const int *nodes", "ARG4 (r4)": "int *status", "ARG5 (r5)": "int flags"}, "345": {"NR": "345", "SYSCALL NAME": "getcpu", "references": "man/ cs/", "r7": "159", "ARG0 (r0)": "unsigned *cpu", "ARG1 (r1)": "unsigned *node", "ARG2 (r2)": "struct getcpu_cache *cache", "ARG3 (r3)": "-", "ARG4 (r4)": "-", "ARG5 (r5)": "-"}, "346": {"NR": "346", "SYSCALL NAME": "epoll_pwait", "references": "man/ cs/", "r7": "15A", "ARG0 (r0)": "int epfd", "ARG1 (r1)": "struct epoll_event *events", "ARG2 (r2)": "int maxevents", "ARG3 (r3)": "int timeout", "ARG4 (r4)": "const sigset_t *sigmask", "ARG5 (r5)": "size_t sigsetsize"}, "347": {"NR": "347", "SYSCALL NAME": "kexec_load", "references": "man/ cs/", "r7": "15B", "ARG0 (r0)": "unsigned long entry", "ARG1 (r1)": "unsigned long nr_segments", "ARG2 (r2)": "struct kexec_segment *segments", "ARG3 (r3)": "unsigned long flags", "ARG4 (r4)": "-", "ARG5 (r5)": "-"}, "348": {"NR": "348", "SYSCALL NAME": "utimensat", "references": "man/ cs/", "r7": "15C", "ARG0 (r0)": "int dfd", "ARG1 (r1)": "const char *filename", "ARG2 (r2)": "struct __kernel_timespec *utimes", "ARG3 (r3)": "int flags", "ARG4 (r4)": "-", "ARG5 (r5)": "-"}, "349": {"NR": "349", "SYSCALL NAME": "signalfd", "references": "man/ cs/", "r7": "15D", "ARG0 (r0)": "int ufd", "ARG1 (r1)": "sigset_t *user_mask", "ARG2 (r2)": "size_t sizemask", "ARG3 (r3)": "-", "ARG4 (r4)": "-", "ARG5 (r5)": "-"}, "350": {"NR": "350", "SYSCALL NAME": "timerfd_create", "references": "man/ cs/", "r7": "15E", "ARG0 (r0)": "int clockid", "ARG1 (r1)": "int flags", "ARG2 (r2)": "-", "ARG3 (r3)": "-", "ARG4 (r4)": "-", "ARG5 (r5)": "-"}, "351": {"NR": "351", "SYSCALL NAME": "eventfd", "references": "man/ cs/", "r7": "15F", "ARG0 (r0)": "unsigned int count", "ARG1 (r1)": "-", "ARG2 (r2)": "-", "ARG3 (r3)": "-", "ARG4 (r4)": "-", "ARG5 (r5)": "-"}, "352": {"NR": "352", "SYSCALL NAME": "fallocate", "references": "man/ cs/", "r7": "160", "ARG0 (r0)": "int fd", "ARG1 (r1)": "int mode", "ARG2 (r2)": "loff_t offset", "ARG3 (r3)": "loff_t len", "ARG4 (r4)": "-", "ARG5 (r5)": "-"}, "353": {"NR": "353", "SYSCALL NAME": "timerfd_settime", "references": "man/ cs/", "r7": "161", "ARG0 (r0)": "int ufd", "ARG1 (r1)": "int flags", "ARG2 (r2)": "const struct __kernel_itimerspec *utmr", "ARG3 (r3)": "struct __kernel_itimerspec *otmr", "ARG4 (r4)": "-", "ARG5 (r5)": "-"}, "354": {"NR": "354", "SYSCALL NAME": "timerfd_gettime", "references": "man/ cs/", "r7": "162", "ARG0 (r0)": "int ufd", "ARG1 (r1)": "struct __kernel_itimerspec *otmr", "ARG2 (r2)": "-", "ARG3 (r3)": "-", "ARG4 (r4)": "-", "ARG5 (r5)": "-"}, "355": {"NR": "355", "SYSCALL NAME": "signalfd4", "references": "man/ cs/", "r7": "163", "ARG0 (r0)": "int ufd", "ARG1 (r1)": "sigset_t *user_mask", "ARG2 (r2)": "size_t sizemask", "ARG3 (r3)": "int flags", "ARG4 (r4)": "-", "ARG5 (r5)": "-"}, "356": {"NR": "356", "SYSCALL NAME": "eventfd2", "references": "man/ cs/", "r7": "164", "ARG0 (r0)": "unsigned int count", "ARG1 (r1)": "int flags", "ARG2 (r2)": "-", "ARG3 (r3)": "-", "ARG4 (r4)": "-", "ARG5 (r5)": "-"}, "357": {"NR": "357", "SYSCALL NAME": "epoll_create1", "references": "man/ cs/", "r7": "165", "ARG0 (r0)": "int flags", "ARG1 (r1)": "-", "ARG2 (r2)": "-", "ARG3 (r3)": "-", "ARG4 (r4)": "-", "ARG5 (r5)": "-"}, "358": {"NR": "358", "SYSCALL NAME": "dup3", "references": "man/ cs/", "r7": "166", "ARG0 (r0)": "unsigned int oldfd", "ARG1 (r1)": "unsigned int newfd", "ARG2 (r2)": "int flags", "ARG3 (r3)": "-", "ARG4 (r4)": "-", "ARG5 (r5)": "-"}, "359": {"NR": "359", "SYSCALL NAME": "pipe2", "references": "man/ cs/", "r7": "167", "ARG0 (r0)": "int *fildes", "ARG1 (r1)": "int flags", "ARG2 (r2)": "-", "ARG3 (r3)": "-", "ARG4 (r4)": "-", "ARG5 (r5)": "-"}, "360": {"NR": "360", "SYSCALL NAME": "inotify_init1", "references": "man/ cs/", "r7": "168", "ARG0 (r0)": "int flags", "ARG1 (r1)": "-", "ARG2 (r2)": "-", "ARG3 (r3)": "-", "ARG4 (r4)": "-", "ARG5 (r5)": "-"}, "361": {"NR": "361", "SYSCALL NAME": "preadv", "references": "man/ cs/", "r7": "169", "ARG0 (r0)": "unsigned long fd", "ARG1 (r1)": "const struct iovec *vec", "ARG2 (r2)": "unsigned long vlen", "ARG3 (r3)": "unsigned long pos_l", "ARG4 (r4)": "unsigned long pos_h", "ARG5 (r5)": "-"}, "362": {"NR": "362", "SYSCALL NAME": "pwritev", "references": "man/ cs/", "r7": "16A", "ARG0 (r0)": "unsigned long fd", "ARG1 (r1)": "const struct iovec *vec", "ARG2 (r2)": "unsigned long vlen", "ARG3 (r3)": "unsigned long pos_l", "ARG4 (r4)": "unsigned long pos_h", "ARG5 (r5)": "-"}, "363": {"NR": "363", "SYSCALL NAME": "rt_tgsigqueueinfo", "references": "man/ cs/", "r7": "16B", "ARG0 (r0)": "pid_t tgid", "ARG1 (r1)": "pid_t pid", "ARG2 (r2)": "int sig", "ARG3 (r3)": "siginfo_t *uinfo", "ARG4 (r4)": "-", "ARG5 (r5)": "-"}, "364": {"NR": "364", "SYSCALL NAME": "perf_event_open", "references": "man/ cs/", "r7": "16C", "ARG0 (r0)": "struct perf_event_attr *attr_uptr", "ARG1 (r1)": "pid_t pid", "ARG2 (r2)": "int cpu", "ARG3 (r3)": "int group_fd", "ARG4 (r4)": "unsigned long flags", "ARG5 (r5)": "-"}, "365": {"NR": "365", "SYSCALL NAME": "recvmmsg", "references": "man/ cs/", "r7": "16D", "ARG0 (r0)": "int fd", "ARG1 (r1)": "struct mmsghdr *msg", "ARG2 (r2)": "unsigned int vlen", "ARG3 (r3)": "unsigned flags", "ARG4 (r4)": "struct __kernel_timespec *timeout", "ARG5 (r5)": "-"}, "366": {"NR": "366", "SYSCALL NAME": "accept4", "references": "man/ cs/", "r7": "16E", "ARG0 (r0)": "int", "ARG1 (r1)": "struct sockaddr *", "ARG2 (r2)": "int *", "ARG3 (r3)": "int", "ARG4 (r4)": "-", "ARG5 (r5)": "-"}, "367": {"NR": "367", "SYSCALL NAME": "fanotify_init", "references": "man/ cs/", "r7": "16F", "ARG0 (r0)": "unsigned int flags", "ARG1 (r1)": "unsigned int event_f_flags", "ARG2 (r2)": "-", "ARG3 (r3)": "-", "ARG4 (r4)": "-", "ARG5 (r5)": "-"}, "368": {"NR": "368", "SYSCALL NAME": "fanotify_mark", "references": "man/ cs/", "r7": "170", "ARG0 (r0)": "int fanotify_fd", "ARG1 (r1)": "unsigned int flags", "ARG2 (r2)": "u64 mask", "ARG3 (r3)": "int fd", "ARG4 (r4)": "const char *pathname", "ARG5 (r5)": "-"}, "369": {"NR": "369", "SYSCALL NAME": "prlimit64", "references": "man/ cs/", "r7": "171", "ARG0 (r0)": "pid_t pid", "ARG1 (r1)": "unsigned int resource", "ARG2 (r2)": "const struct rlimit64 *new_rlim", "ARG3 (r3)": "struct rlimit64 *old_rlim", "ARG4 (r4)": "-", "ARG5 (r5)": "-"}, "370": {"NR": "370", "SYSCALL NAME": "name_to_handle_at", "references": "man/ cs/", "r7": "172", "ARG0 (r0)": "int dfd", "ARG1 (r1)": "const char *name", "ARG2 (r2)": "struct file_handle *handle", "ARG3 (r3)": "int *mnt_id", "ARG4 (r4)": "int flag", "ARG5 (r5)": "-"}, "371": {"NR": "371", "SYSCALL NAME": "open_by_handle_at", "references": "man/ cs/", "r7": "173", "ARG0 (r0)": "int mountdirfd", "ARG1 (r1)": "struct file_handle *handle", "ARG2 (r2)": "int flags", "ARG3 (r3)": "-", "ARG4 (r4)": "-", "ARG5 (r5)": "-"}, "372": {"NR": "372", "SYSCALL NAME": "clock_adjtime", "references": "man/ cs/", "r7": "174", "ARG0 (r0)": "clockid_t which_clock", "ARG1 (r1)": "struct __kernel_timex *tx", "ARG2 (r2)": "-", "ARG3 (r3)": "-", "ARG4 (r4)": "-", "ARG5 (r5)": "-"}, "373": {"NR": "373", "SYSCALL NAME": "syncfs", "references": "man/ cs/", "r7": "175", "ARG0 (r0)": "int fd", "ARG1 (r1)": "-", "ARG2 (r2)": "-", "ARG3 (r3)": "-", "ARG4 (r4)": "-", "ARG5 (r5)": "-"}, "374": {"NR": "374", "SYSCALL NAME": "sendmmsg", "references": "man/ cs/", "r7": "176", "ARG0 (r0)": "int fd", "ARG1 (r1)": "struct mmsghdr *msg", "ARG2 (r2)": "unsigned int vlen", "ARG3 (r3)": "unsigned flags", "ARG4 (r4)": "-", "ARG5 (r5)": "-"}, "375": {"NR": "375", "SYSCALL NAME": "setns", "references": "man/ cs/", "r7": "177", "ARG0 (r0)": "int fd", "ARG1 (r1)": "int nstype", "ARG2 (r2)": "-", "ARG3 (r3)": "-", "ARG4 (r4)": "-", "ARG5 (r5)": "-"}, "376": {"NR": "376", "SYSCALL NAME": "process_vm_readv", "references": "man/ cs/", "r7": "178", "ARG0 (r0)": "pid_t pid", "ARG1 (r1)": "const struct iovec *lvec", "ARG2 (r2)": "unsigned long liovcnt", "ARG3 (r3)": "const struct iovec *rvec", "ARG4 (r4)": "unsigned long riovcnt", "ARG5 (r5)": "unsigned long flags"}, "377": {"NR": "377", "SYSCALL NAME": "process_vm_writev", "references": "man/ cs/", "r7": "179", "ARG0 (r0)": "pid_t pid", "ARG1 (r1)": "const struct iovec *lvec", "ARG2 (r2)": "unsigned long liovcnt", "ARG3 (r3)": "const struct iovec *rvec", "ARG4 (r4)": "unsigned long riovcnt", "ARG5 (r5)": "unsigned long flags"}, "378": {"NR": "378", "SYSCALL NAME": "kcmp", "references": "man/ cs/", "r7": "17A", "ARG0 (r0)": "pid_t pid1", "ARG1 (r1)": "pid_t pid2", "ARG2 (r2)": "int type", "ARG3 (r3)": "unsigned long idx1", "ARG4 (r4)": "unsigned long idx2", "ARG5 (r5)": "-"}, "379": {"NR": "379", "SYSCALL NAME": "finit_module", "references": "man/ cs/", "r7": "17B", "ARG0 (r0)": "int fd", "ARG1 (r1)": "const char *uargs", "ARG2 (r2)": "int flags", "ARG3 (r3)": "-", "ARG4 (r4)": "-", "ARG5 (r5)": "-"}, "380": {"NR": "380", "SYSCALL NAME": "sched_setattr", "references": "man/ cs/", "r7": "17C", "ARG0 (r0)": "pid_t pid", "ARG1 (r1)": "struct sched_attr *attr", "ARG2 (r2)": "unsigned int flags", "ARG3 (r3)": "-", "ARG4 (r4)": "-", "ARG5 (r5)": "-"}, "381": {"NR": "381", "SYSCALL NAME": "sched_getattr", "references": "man/ cs/", "r7": "17D", "ARG0 (r0)": "pid_t pid", "ARG1 (r1)": "struct sched_attr *attr", "ARG2 (r2)": "unsigned int size", "ARG3 (r3)": "unsigned int flags", "ARG4 (r4)": "-", "ARG5 (r5)": "-"}, "382": {"NR": "382", "SYSCALL NAME": "renameat2", "references": "man/ cs/", "r7": "17E", "ARG0 (r0)": "int olddfd", "ARG1 (r1)": "const char *oldname", "ARG2 (r2)": "int newdfd", "ARG3 (r3)": "const char *newname", "ARG4 (r4)": "unsigned int flags", "ARG5 (r5)": "-"}, "383": {"NR": "383", "SYSCALL NAME": "seccomp", "references": "man/ cs/", "r7": "17F", "ARG0 (r0)": "unsigned int op", "ARG1 (r1)": "unsigned int flags", "ARG2 (r2)": "void *uargs", "ARG3 (r3)": "-", "ARG4 (r4)": "-", "ARG5 (r5)": "-"}, "384": {"NR": "384", "SYSCALL NAME": "getrandom", "references": "man/ cs/", "r7": "180", "ARG0 (r0)": "char *buf", "ARG1 (r1)": "size_t count", "ARG2 (r2)": "unsigned int flags", "ARG3 (r3)": "-", "ARG4 (r4)": "-", "ARG5 (r5)": "-"}, "385": {"NR": "385", "SYSCALL NAME": "memfd_create", "references": "man/ cs/", "r7": "181", "ARG0 (r0)": "const char *uname_ptr", "ARG1 (r1)": "unsigned int flags", "ARG2 (r2)": "-", "ARG3 (r3)": "-", "ARG4 (r4)": "-", "ARG5 (r5)": "-"}, "386": {"NR": "386", "SYSCALL NAME": "bpf", "references": "man/ cs/", "r7": "182", "ARG0 (r0)": "int cmd", "ARG1 (r1)": "union bpf_attr *attr", "ARG2 (r2)": "unsigned int size", "ARG3 (r3)": "-", "ARG4 (r4)": "-", "ARG5 (r5)": "-"}, "387": {"NR": "387", "SYSCALL NAME": "execveat", "references": "man/ cs/", "r7": "183", "ARG0 (r0)": "int dfd", "ARG1 (r1)": "const char *filename", "ARG2 (r2)": "const char *const *argv", "ARG3 (r3)": "const char *const *envp", "ARG4 (r4)": "int flags", "ARG5 (r5)": "-"}, "388": {"NR": "388", "SYSCALL NAME": "userfaultfd", "references": "man/ cs/", "r7": "184", "ARG0 (r0)": "int flags", "ARG1 (r1)": "-", "ARG2 (r2)": "-", "ARG3 (r3)": "-", "ARG4 (r4)": "-", "ARG5 (r5)": "-"}, "389": {"NR": "389", "SYSCALL NAME": "membarrier", "references": "man/ cs/", "r7": "185", "ARG0 (r0)": "int cmd", "ARG1 (r1)": "int flags", "ARG2 (r2)": "-", "ARG3 (r3)": "-", "ARG4 (r4)": "-", "ARG5 (r5)": "-"}, "390": {"NR": "390", "SYSCALL NAME": "mlock2", "references": "man/ cs/", "r7": "186", "ARG0 (r0)": "unsigned long start", "ARG1 (r1)": "size_t len", "ARG2 (r2)": "int flags", "ARG3 (r3)": "-", "ARG4 (r4)": "-", "ARG5 (r5)": "-"}, "391": {"NR": "391", "SYSCALL NAME": "copy_file_range", "references": "man/ cs/", "r7": "187", "ARG0 (r0)": "int fd_in", "ARG1 (r1)": "loff_t *off_in", "ARG2 (r2)": "int fd_out", "ARG3 (r3)": "loff_t *off_out", "ARG4 (r4)": "size_t len", "ARG5 (r5)": "unsigned int flags"}, "392": {"NR": "392", "SYSCALL NAME": "preadv2", "references": "man/ cs/", "r7": "188", "ARG0 (r0)": "unsigned long fd", "ARG1 (r1)": "const struct iovec *vec", "ARG2 (r2)": "unsigned long vlen", "ARG3 (r3)": "unsigned long pos_l", "ARG4 (r4)": "unsigned long pos_h", "ARG5 (r5)": "rwf_t flags"}, "393": {"NR": "393", "SYSCALL NAME": "pwritev2", "references": "man/ cs/", "r7": "189", "ARG0 (r0)": "unsigned long fd", "ARG1 (r1)": "const struct iovec *vec", "ARG2 (r2)": "unsigned long vlen", "ARG3 (r3)": "unsigned long pos_l", "ARG4 (r4)": "unsigned long pos_h", "ARG5 (r5)": "rwf_t flags"}, "394": {"NR": "394", "SYSCALL NAME": "pkey_mprotect", "references": "man/ cs/", "r7": "18A", "ARG0 (r0)": "unsigned long start", "ARG1 (r1)": "size_t len", "ARG2 (r2)": "unsigned long prot", "ARG3 (r3)": "int pkey", "ARG4 (r4)": "-", "ARG5 (r5)": "-"}, "395": {"NR": "395", "SYSCALL NAME": "pkey_alloc", "references": "man/ cs/", "r7": "18B", "ARG0 (r0)": "unsigned long flags", "ARG1 (r1)": "unsigned long init_val", "ARG2 (r2)": "-", "ARG3 (r3)": "-", "ARG4 (r4)": "-", "ARG5 (r5)": "-"}, "396": {"NR": "396", "SYSCALL NAME": "pkey_free", "references": "man/ cs/", "r7": "18C", "ARG0 (r0)": "int pkey", "ARG1 (r1)": "-", "ARG2 (r2)": "-", "ARG3 (r3)": "-", "ARG4 (r4)": "-", "ARG5 (r5)": "-"}, "397": {"NR": "397", "SYSCALL NAME": "statx", "references": "man/ cs/", "r7": "18D", "ARG0 (r0)": "int dfd", "ARG1 (r1)": "const char *path", "ARG2 (r2)": "unsigned flags", "ARG3 (r3)": "unsigned mask", "ARG4 (r4)": "struct statx *buffer", "ARG5 (r5)": "-"}, "983041": {"NR": "983041", "SYSCALL NAME": "ARM_breakpoint", "references": "man/ cs/", "r7": "F0001", "ARG0 (r0)": "?", "ARG1 (r1)": "?", "ARG2 (r2)": "?", "ARG3 (r3)": "?", "ARG4 (r4)": "?", "ARG5 (r5)": "?"}, "983042": {"NR": "983042", "SYSCALL NAME": "ARM_cacheflush", "references": "man/ cs/", "r7": "F0002", "ARG0 (r0)": "?", "ARG1 (r1)": "?", "ARG2 (r2)": "?", "ARG3 (r3)": "?", "ARG4 (r4)": "?", "ARG5 (r5)": "?"}, "983043": {"NR": "983043", "SYSCALL NAME": "ARM_usr26", "references": "man/ cs/", "r7": "F0003", "ARG0 (r0)": "?", "ARG1 (r1)": "?", "ARG2 (r2)": "?", "ARG3 (r3)": "?", "ARG4 (r4)": "?", "ARG5 (r5)": "?"}, "983044": {"NR": "983044", "SYSCALL NAME": "ARM_usr32", "references": "man/ cs/", "r7": "F0004", "ARG0 (r0)": "?", "ARG1 (r1)": "?", "ARG2 (r2)": "?", "ARG3 (r3)": "?", "ARG4 (r4)": "?", "ARG5 (r5)": "?"}, "983045": {"NR": "983045", "SYSCALL NAME": "ARM_set_tls", "references": "man/ cs/", "r7": "F0005", "ARG0 (r0)": "?", "ARG1 (r1)": "?", "ARG2 (r2)": "?", "ARG3 (r3)": "?", "ARG4 (r4)": "?", "ARG5 (r5)": "?"}}